{"name":"iow","id":104,"All Time":{"Daily":{"Win Percent":{"value":0,"rank":323},"Points":{"value":0,"rank":356},"Points Per Game":{"value":0,"rank":356},"Games":{"value":0,"rank":356},"Games Per Hour":{"value":0,"rank":356},"Wins":{"value":0,"rank":352},"Ties":{"value":0,"rank":319},"Losses":{"value":0,"rank":353},"Saves":{"value":0,"rank":323},"Save Percent":{"value":0,"rank":323},"Tags":{"value":0,"rank":356},"Tags Per Game":{"value":0,"rank":356},"Tags Per Hour":{"value":0,"rank":356},"Popped":{"value":0,"rank":355},"Popped Per Game":{"value":0,"rank":355},"Popped Per Hour":{"value":0,"rank":355},"Tags Per Pop":{"value":0,"rank":356},"Grabs":{"value":0,"rank":355},"Grabs Per Game":{"value":0,"rank":355},"Grabs Per Hour":{"value":0,"rank":355},"Captures":{"value":0,"rank":353},"Captures Per Game":{"value":0,"rank":353},"Captures Per Hour":{"value":0,"rank":353},"Captures Per Grab":{"value":0,"rank":353},"Hold":{"value":0,"rank":355},"Hold Per Game":{"value":0,"rank":355},"Hold Per Grab":{"value":0,"rank":355},"Hold Per Hour":{"value":0,"rank":355},"Hold Per Cap":{"value":0,"rank":355},"Prevent":{"value":0,"rank":356},"Prevent Per Game":{"value":0,"rank":356},"Prevent Per Hour":{"value":0,"rank":356},"Returns":{"value":0,"rank":356},"Returns Per Game":{"value":0,"rank":356},"Returns Per Hour":{"value":0,"rank":356},"Support":{"value":0,"rank":355},"Support Per Game":{"value":0,"rank":355},"Support Per Hour":{"value":0,"rank":355},"Non-Return Tags":{"value":0,"rank":352},"Prevent Per Return":{"value":0,"rank":356},"Power-up Percent":{"value":0,"rank":354},"Time Played":{"value":0,"rank":356},"Disconnects":{"value":0,"rank":328},"Disconnects Per Game":{"value":0,"rank":328}},"Weekly":{"Win Percent":{"value":0.5033557046979866,"rank":90},"Points":{"value":6312,"rank":2},"Points Per Game":{"value":21.04,"rank":71},"Games":{"value":300,"rank":4},"Games Per Hour":{"value":11.589723778249953,"rank":225},"Wins":{"value":150,"rank":5},"Ties":{"value":6,"rank":3},"Losses":{"value":140,"rank":4},"Saves":{"value":3,"rank":20},"Save Percent":{"value":0.6,"rank":32},"Tags":{"value":1832,"rank":4},"Tags Per Game":{"value":6.1066666666666665,"rank":135},"Tags Per Hour":{"value":70.77457987251303,"rank":176},"Popped":{"value":2036,"rank":4},"Popped Per Game":{"value":6.786666666666667,"rank":108},"Popped Per Hour":{"value":78.65559204172301,"rank":188},"Tags Per Pop":{"value":0.899803536345776,"rank":141},"Grabs":{"value":1432,"rank":5},"Grabs Per Game":{"value":0.7033398821218074,"rank":219},"Grabs Per Hour":{"value":55.321614834846436,"rank":220},"Captures":{"value":110,"rank":12},"Captures Per Game":{"value":0.36666666666666664,"rank":198},"Captures Per Hour":{"value":4.2495653853583155,"rank":209},"Captures Per Grab":{"value":0.07681564245810056,"rank":185},"Hold":{"value":10388,"rank":7},"Hold Per Game":{"value":34.626666666666665,"rank":188},"Hold Per Grab":{"value":7.254189944134078,"rank":170},"Hold Per Hour":{"value":401.31350202820164,"rank":211},"Hold Per Cap":{"value":94.43636363636364,"rank":69},"Prevent":{"value":15726,"rank":1},"Prevent Per Game":{"value":52.42,"rank":12},"Prevent Per Hour":{"value":607.5333204558625,"rank":31},"Returns":{"value":1531,"rank":4},"Returns Per Game":{"value":5.1033333333333335,"rank":110},"Returns Per Hour":{"value":59.14622368166892,"rank":153},"Support":{"value":4581,"rank":6},"Support Per Game":{"value":15.27,"rank":177},"Support Per Hour":{"value":176.97508209387678,"rank":227},"Non-Return Tags":{"value":301,"rank":12},"Prevent Per Return":{"value":10.271717831482691,"rank":25},"Power-up Percent":{"value":0.06,"rank":229},"Time Played":{"value":93186,"rank":3},"Disconnects":{"value":2,"rank":133},"Disconnects Per Game":{"value":0.006666666666666667,"rank":181}},"Monthly":{"Win Percent":{"value":0.48610547078958055,"rank":173},"Points":{"value":16797,"rank":20},"Points Per Game":{"value":20.092105263157894,"rank":122},"Games":{"value":836,"rank":22},"Games Per Hour":{"value":11.861053527654509,"rank":255},"Wins":{"value":399,"rank":33},"Ties":{"value":13,"rank":9},"Losses":{"value":394,"rank":17},"Saves":{"value":11,"rank":29},"Save Percent":{"value":0.42,"rank":66},"Tags":{"value":4877,"rank":32},"Tags Per Game":{"value":5.833732057416268,"rank":177},"Tags Per Hour":{"value":69.19420819900843,"rank":214},"Popped":{"value":5360,"rank":29},"Popped Per Game":{"value":6.411483253588517,"rank":145},"Popped Per Hour":{"value":76.04694606247389,"rank":232},"Tags Per Pop":{"value":0.9098880597014926,"rank":166},"Grabs":{"value":3856,"rank":49},"Grabs Per Game":{"value":0.7194029850746269,"rank":242},"Grabs Per Hour":{"value":54.70840000315286,"rank":249},"Captures":{"value":310,"rank":70},"Captures Per Game":{"value":0.3708133971291866,"rank":216},"Captures Per Hour":{"value":4.398237552120691,"rank":235},"Captures Per Grab":{"value":0.0803941908713693,"rank":204},"Hold":{"value":27430,"rank":64},"Hold Per Game":{"value":32.811004784689,"rank":217},"Hold Per Grab":{"value":7.113589211618257,"rank":202},"Hold Per Hour":{"value":389.1730840473244,"rank":239},"Hold Per Cap":{"value":88.48387096774194,"rank":89},"Prevent":{"value":44687,"rank":5},"Prevent Per Game":{"value":53.45334928229665,"rank":11},"Prevent Per Hour":{"value":634.0130370697334,"rank":21},"Returns":{"value":4150,"rank":24},"Returns Per Game":{"value":4.964114832535885,"rank":138},"Returns Per Hour":{"value":58.87963174613183,"rank":191},"Support":{"value":13344,"rank":28},"Support Per Game":{"value":15.961722488038278,"rank":191},"Support Per Hour":{"value":189.32284482418873,"rank":249},"Non-Return Tags":{"value":727,"rank":78},"Prevent Per Return":{"value":10.767951807228915,"rank":11},"Power-up Percent":{"value":0.06,"rank":253},"Time Played":{"value":253738,"rank":13},"Disconnects":{"value":15,"rank":106},"Disconnects Per Game":{"value":0.017942583732057416,"rank":164}},"All":{"Win Percent":{"value":0.4478067088904527,"rank":363},"Points":{"value":82823,"rank":250},"Points Per Game":{"value":18.87058555479608,"rank":186},"Games":{"value":4389,"rank":251},"Games Per Hour":{"value":12.166104704390388,"rank":409},"Wins":{"value":1909,"rank":267},"Ties":{"value":50,"rank":148},"Losses":{"value":2224,"rank":202},"Saves":{"value":49,"rank":123},"Save Percent":{"value":0.28,"rank":300},"Tags":{"value":23529,"rank":252},"Tags Per Game":{"value":5.360902255639098,"rank":272},"Tags Per Hour":{"value":65.22129815210788,"rank":337},"Popped":{"value":27953,"rank":242},"Popped Per Game":{"value":6.36887673729779,"rank":162},"Popped Per Hour":{"value":77.48442123532115,"rank":306},"Tags Per Pop":{"value":0.8417343397846385,"rank":278},"Grabs":{"value":19860,"rank":259},"Grabs Per Game":{"value":0.7104783028655243,"rank":364},"Grabs Per Hour":{"value":55.05100009778837,"rank":356},"Captures":{"value":1311,"rank":288},"Captures Per Game":{"value":0.2987012987012987,"rank":392},"Captures Per Hour":{"value":3.634031275337389,"rank":408},"Captures Per Grab":{"value":0.06601208459214501,"rank":397},"Hold":{"value":137494,"rank":268},"Hold Per Game":{"value":31.326953748006378,"rank":356},"Hold Per Grab":{"value":6.923162134944612,"rank":379},"Hold Per Hour":{"value":381.12699936784054,"rank":388},"Hold Per Cap":{"value":104.87719298245614,"rank":38},"Prevent":{"value":223383,"rank":148},"Prevent Per Game":{"value":50.896103896103895,"rank":6},"Prevent Per Hour":{"value":619.2073290455317,"rank":15},"Returns":{"value":20155,"rank":243},"Returns Per Game":{"value":4.5921622237411714,"rank":183},"Returns Per Hour":{"value":55.868726433581294,"rank":257},"Support":{"value":68114,"rank":218},"Support Per Game":{"value":15.519252677147414,"rank":80},"Support Per Hour":{"value":188.8088530040663,"rank":157},"Non-Return Tags":{"value":3374,"rank":277},"Prevent Per Return":{"value":11.083254775489953,"rank":11},"Power-up Percent":{"value":0.06,"rank":410},"Time Played":{"value":1298723,"rank":245},"Disconnects":{"value":82,"rank":286},"Disconnects Per Game":{"value":0.018683071314650263,"rank":282}}},"Rolling 300":{"All":{"Win Percent":{"value":0.5033557046979866,"rank":307},"Points":{"value":6312,"rank":195},"Points Per Game":{"value":21.04,"rank":195},"Games":{"value":300,"rank":311},"Games Per Hour":{"value":11.589723778249953,"rank":424},"Wins":{"value":150,"rank":322},"Ties":{"value":6,"rank":34},"Losses":{"value":140,"rank":41},"Saves":{"value":3,"rank":261},"Save Percent":{"value":0.6,"rank":57},"Tags":{"value":1832,"rank":277},"Tags Per Game":{"value":6.1066666666666665,"rank":279},"Tags Per Hour":{"value":70.77457987251303,"rank":348},"Popped":{"value":2036,"rank":94},"Popped Per Game":{"value":6.786666666666667,"rank":97},"Popped Per Hour":{"value":78.65559204172301,"rank":281},"Tags Per Pop":{"value":0.899803536345776,"rank":309},"Grabs":{"value":1432,"rank":336},"Grabs Per Game":{"value":0.7033398821218074,"rank":406},"Grabs Per Hour":{"value":55.321614834846436,"rank":395},"Captures":{"value":110,"rank":378},"Captures Per Game":{"value":0.36666666666666664,"rank":381},"Captures Per Hour":{"value":4.2495653853583155,"rank":400},"Captures Per Grab":{"value":0.07681564245810056,"rank":375},"Hold":{"value":10388,"rank":357},"Hold Per Game":{"value":34.626666666666665,"rank":360},"Hold Per Grab":{"value":7.254189944134078,"rank":354},"Hold Per Hour":{"value":401.31350202820164,"rank":392},"Hold Per Cap":{"value":94.43636363636364,"rank":53},"Prevent":{"value":15726,"rank":14},"Prevent Per Game":{"value":52.42,"rank":14},"Prevent Per Hour":{"value":607.5333204558625,"rank":38},"Returns":{"value":1531,"rank":220},"Returns Per Game":{"value":5.1033333333333335,"rank":220},"Returns Per Hour":{"value":59.14622368166892,"rank":305},"Support":{"value":4581,"rank":243},"Support Per Game":{"value":15.27,"rank":249},"Support Per Hour":{"value":176.97508209387678,"rank":352},"Non-Return Tags":{"value":301,"rank":367},"Prevent Per Return":{"value":10.271717831482691,"rank":26},"Power-up Percent":{"value":0.06,"rank":409},"Time Played":{"value":93186,"rank":7},"Disconnects":{"value":2,"rank":309},"Disconnects Per Game":{"value":0.006666666666666667,"rank":310}},"CTF":{"Win Percent":{"value":0.5097666252103299,"rank":301},"Points":{"value":4611,"rank":165},"Points Per Game":{"value":22.492682926829268,"rank":117},"Games":{"value":205,"rank":264},"Games Per Hour":{"value":10.885758536765248,"rank":427},"Wins":{"value":104,"rank":322},"Ties":{"value":6,"rank":10},"Losses":{"value":92,"rank":54},"Saves":{"value":2,"rank":283},"Save Percent":{"value":0.67,"rank":46},"Tags":{"value":1303,"rank":254},"Tags Per Game":{"value":6.35609756097561,"rank":227},"Tags Per Hour":{"value":69.19094328490301,"rank":331},"Popped":{"value":1351,"rank":104},"Popped Per Game":{"value":6.590243902439024,"rank":86},"Popped Per Hour":{"value":71.73980382034073,"rank":266},"Tags Per Pop":{"value":0.9644707623982235,"rank":286},"Grabs":{"value":899,"rank":292},"Grabs Per Game":{"value":0.6654330125832717,"rank":399},"Grabs Per Hour":{"value":47.73803377830223,"rank":378},"Captures":{"value":69,"rank":372},"Captures Per Game":{"value":0.33658536585365856,"rank":377},"Captures Per Hour":{"value":3.663987019691718,"rank":397},"Captures Per Grab":{"value":0.07675194660734148,"rank":389},"Hold":{"value":8054,"rank":334},"Hold Per Game":{"value":39.28780487804878,"rank":337},"Hold Per Grab":{"value":8.958843159065628,"rank":341},"Hold Per Hour":{"value":427.67755734198687,"rank":383},"Hold Per Cap":{"value":116.72463768115942,"rank":33},"Prevent":{"value":8479,"rank":31},"Prevent Per Game":{"value":41.360975609756096,"rank":26},"Prevent Per Hour":{"value":450.2455933328417,"rank":59},"Returns":{"value":1114,"rank":171},"Returns Per Game":{"value":5.434146341463415,"rank":152},"Returns Per Hour":{"value":59.15480492661701,"rank":256},"Support":{"value":2219,"rank":167},"Support Per Game":{"value":10.824390243902439,"rank":158},"Support Per Hour":{"value":117.83169850283944,"rank":325},"Non-Return Tags":{"value":189,"rank":383},"Prevent Per Return":{"value":7.611310592459605,"rank":11},"Power-up Percent":{"value":0.06,"rank":413},"Time Played":{"value":67795,"rank":24},"Disconnects":{"value":2,"rank":277},"Disconnects Per Game":{"value":0.00975609756097561,"rank":258}},"Neutral":{"Win Percent":{"value":0.48936170212765956,"rank":210},"Points":{"value":1701,"rank":234},"Points Per Game":{"value":17.905263157894737,"rank":297},"Games":{"value":95,"rank":165},"Games Per Hour":{"value":13.469339529754638,"rank":274},"Wins":{"value":46,"rank":328},"Ties":{"value":0,"rank":363},"Losses":{"value":48,"rank":46},"Saves":{"value":1,"rank":211},"Save Percent":{"value":0.5,"rank":150},"Tags":{"value":529,"rank":312},"Tags Per Game":{"value":5.568421052631579,"rank":374},"Tags Per Hour":{"value":75.00295380252845,"rank":392},"Popped":{"value":685,"rank":197},"Popped Per Game":{"value":7.2105263157894735,"rank":252},"Popped Per Hour":{"value":97.12102713559922,"rank":325},"Tags Per Pop":{"value":0.7722627737226277,"rank":395},"Grabs":{"value":533,"rank":294},"Grabs Per Game":{"value":0.7781021897810219,"rank":385},"Grabs Per Hour":{"value":75.57008388799181,"rank":387},"Captures":{"value":41,"rank":363},"Captures Per Game":{"value":0.43157894736842106,"rank":358},"Captures Per Hour":{"value":5.813083375999369,"rank":362},"Captures Per Grab":{"value":0.07692307692307693,"rank":359},"Hold":{"value":2334,"rank":364},"Hold Per Game":{"value":24.568421052631578,"rank":386},"Hold Per Grab":{"value":4.378986866791744,"rank":397},"Hold Per Hour":{"value":330.9204048678666,"rank":396},"Hold Per Cap":{"value":56.926829268292686,"rank":141},"Prevent":{"value":7247,"rank":40},"Prevent Per Game":{"value":76.28421052631579,"rank":25},"Prevent Per Hour":{"value":1027.4979323382302,"rank":21},"Returns":{"value":417,"rank":312},"Returns Per Game":{"value":4.389473684210526,"rank":380},"Returns Per Hour":{"value":59.12331140955457,"rank":402},"Support":{"value":2362,"rank":263},"Support Per Game":{"value":24.86315789473684,"rank":313},"Support Per Hour":{"value":334.89031546611,"rank":361},"Non-Return Tags":{"value":112,"rank":224},"Prevent Per Return":{"value":17.378896882494004,"rank":26},"Power-up Percent":{"value":0.09,"rank":336},"Time Played":{"value":25391,"rank":133},"Disconnects":{"value":0,"rank":385},"Disconnects Per Game":{"value":0,"rank":385}}}}
