{"name":"Carrott","id":126,"All Time":{"Daily":{"Win Percent":{"value":0,"rank":281},"Points":{"value":113,"rank":111},"Points Per Game":{"value":12.555555555555555,"rank":133},"Games":{"value":9,"rank":94},"Games Per Hour":{"value":18.01000555864369,"rank":22},"Wins":{"value":6,"rank":70},"Ties":{"value":0,"rank":279},"Losses":{"value":2,"rank":120},"Saves":{"value":0,"rank":281},"Save Percent":{"value":0,"rank":281},"Tags":{"value":41,"rank":104},"Tags Per Game":{"value":4.555555555555555,"rank":118},"Tags Per Hour":{"value":82.0455808782657,"rank":56},"Popped":{"value":51,"rank":103},"Popped Per Game":{"value":5.666666666666667,"rank":113},"Popped Per Hour":{"value":102.05669816564757,"rank":28},"Tags Per Pop":{"value":0.803921568627451,"rank":96},"Grabs":{"value":40,"rank":104},"Grabs Per Game":{"value":0.7843137254901961,"rank":88},"Grabs Per Hour":{"value":80.04446914952752,"rank":36},"Captures":{"value":3,"rank":104},"Captures Per Game":{"value":0.3333333333333333,"rank":106},"Captures Per Hour":{"value":6.003335186214564,"rank":75},"Captures Per Grab":{"value":0.075,"rank":92},"Hold":{"value":239,"rank":114},"Hold Per Game":{"value":26.555555555555557,"rank":128},"Hold Per Grab":{"value":5.975,"rank":128},"Hold Per Hour":{"value":478.2657031684269,"rank":96},"Hold Per Cap":{"value":79.66666666666667,"rank":88},"Prevent":{"value":385,"rank":71},"Prevent Per Game":{"value":42.77777777777778,"rank":31},"Prevent Per Hour":{"value":770.4280155642023,"rank":16},"Returns":{"value":33,"rank":104},"Returns Per Game":{"value":3.6666666666666665,"rank":119},"Returns Per Hour":{"value":66.0366870483602,"rank":59},"Support":{"value":113,"rank":106},"Support Per Game":{"value":12.555555555555555,"rank":122},"Support Per Hour":{"value":226.12562534741522,"rank":67},"Non-Return Tags":{"value":8,"rank":104},"Prevent Per Return":{"value":11.666666666666666,"rank":16},"Power-up Percent":{"value":0.14,"rank":45},"Time Played":{"value":1799,"rank":108},"Disconnects":{"value":1,"rank":46},"Disconnects Per Game":{"value":0.1111111111111111,"rank":30}},"Weekly":{"Win Percent":{"value":0.5298507462686567,"rank":67},"Points":{"value":2450,"rank":68},"Points Per Game":{"value":18.014705882352942,"rank":182},"Games":{"value":136,"rank":58},"Games Per Hour":{"value":13.895274584929759,"rank":58},"Wins":{"value":71,"rank":53},"Ties":{"value":1,"rank":125},"Losses":{"value":54,"rank":69},"Saves":{"value":2,"rank":55},"Save Percent":{"value":0.5,"rank":49},"Tags":{"value":789,"rank":61},"Tags Per Game":{"value":5.801470588235294,"rank":161},"Tags Per Hour":{"value":80.61302681992336,"rank":121},"Popped":{"value":911,"rank":56},"Popped Per Game":{"value":6.698529411764706,"rank":117},"Popped Per Hour":{"value":93.0779054916986,"rank":58},"Tags Per Pop":{"value":0.8660812294182217,"rank":155},"Grabs":{"value":753,"rank":50},"Grabs Per Game":{"value":0.8265642151481888,"rank":110},"Grabs Per Hour":{"value":76.93486590038314,"rank":64},"Captures":{"value":87,"rank":33},"Captures Per Game":{"value":0.6397058823529411,"rank":79},"Captures Per Hour":{"value":8.88888888888889,"rank":62},"Captures Per Grab":{"value":0.11553784860557768,"rank":72},"Hold":{"value":5955,"rank":50},"Hold Per Game":{"value":43.786764705882355,"rank":115},"Hold Per Grab":{"value":7.908366533864542,"rank":117},"Hold Per Hour":{"value":608.4291187739464,"rank":78},"Hold Per Cap":{"value":68.44827586206897,"rank":180},"Prevent":{"value":3242,"rank":113},"Prevent Per Game":{"value":23.83823529411765,"rank":217},"Prevent Per Hour":{"value":331.23882503192846,"rank":210},"Returns":{"value":512,"rank":96},"Returns Per Game":{"value":3.764705882352941,"rank":211},"Returns Per Hour":{"value":52.31162196679438,"rank":200},"Support":{"value":1736,"rank":104},"Support Per Game":{"value":12.764705882352942,"rank":227},"Support Per Hour":{"value":177.3690932311622,"rank":225},"Non-Return Tags":{"value":277,"rank":16},"Prevent Per Return":{"value":6.33203125,"rank":168},"Power-up Percent":{"value":0.2,"rank":20},"Time Played":{"value":35235,"rank":70},"Disconnects":{"value":9,"rank":43},"Disconnects Per Game":{"value":0.0661764705882353,"rank":58}},"Monthly":{"Win Percent":{"value":0.5365853658536586,"rank":129},"Points":{"value":2952,"rank":214},"Points Per Game":{"value":17.676646706586826,"rank":215},"Games":{"value":167,"rank":207},"Games Per Hour":{"value":14.021503370105185,"rank":56},"Wins":{"value":88,"rank":214},"Ties":{"value":1,"rank":220},"Losses":{"value":62,"rank":202},"Saves":{"value":2,"rank":187},"Save Percent":{"value":0.4,"rank":74},"Tags":{"value":973,"rank":214},"Tags Per Game":{"value":5.826347305389222,"rank":179},"Tags Per Hour":{"value":81.69414837791824,"rank":146},"Popped":{"value":1112,"rank":208},"Popped Per Game":{"value":6.658682634730539,"rank":112},"Popped Per Hour":{"value":93.36474100333511,"rank":53},"Tags Per Pop":{"value":0.875,"rank":180},"Grabs":{"value":924,"rank":207},"Grabs Per Game":{"value":0.8309352517985612,"rank":121},"Grabs Per Hour":{"value":77.58005457471373,"rank":74},"Captures":{"value":109,"rank":192},"Captures Per Game":{"value":0.6526946107784432,"rank":89},"Captures Per Hour":{"value":9.151759684679432,"rank":76},"Captures Per Grab":{"value":0.11796536796536797,"rank":88},"Hold":{"value":7345,"rank":204},"Hold Per Game":{"value":43.98203592814371,"rank":125},"Hold Per Grab":{"value":7.949134199134199,"rank":134},"Hold Per Hour":{"value":616.6942649905544,"rank":88},"Hold Per Cap":{"value":67.38532110091744,"rank":203},"Prevent":{"value":3582,"rank":234},"Prevent Per Game":{"value":21.449101796407184,"rank":265},"Prevent Per Hour":{"value":300.7486531240525,"rank":263},"Returns":{"value":636,"rank":223},"Returns Per Game":{"value":3.808383233532934,"rank":238},"Returns Per Hour":{"value":53.399258343634116,"rank":222},"Support":{"value":2050,"rank":227},"Support Per Game":{"value":12.275449101796408,"rank":261},"Support Per Hour":{"value":172.120250950393,"rank":263},"Non-Return Tags":{"value":337,"rank":174},"Prevent Per Return":{"value":5.632075471698113,"rank":226},"Power-up Percent":{"value":0.2,"rank":18},"Time Played":{"value":42877,"rank":212},"Disconnects":{"value":14,"rank":112},"Disconnects Per Game":{"value":0.08383233532934131,"rank":49}},"All":{"Win Percent":{"value":0.5174903651639768,"rank":290},"Points":{"value":137724,"rank":162},"Points Per Game":{"value":18.0385068762279,"rank":258},"Games":{"value":7635,"rank":152},"Games Per Hour":{"value":13.793636439368923,"rank":134},"Wins":{"value":3894,"rank":174},"Ties":{"value":63,"rank":118},"Losses":{"value":2799,"rank":157},"Saves":{"value":62,"rank":93},"Save Percent":{"value":0.36,"rank":186},"Tags":{"value":39762,"rank":173},"Tags Per Game":{"value":5.207858546168959,"rank":292},"Tags Per Hour":{"value":71.83530741351501,"rank":268},"Popped":{"value":51907,"rank":138},"Popped Per Game":{"value":6.798559266535691,"rank":73},"Popped Per Hour":{"value":93.77685483409597,"rank":46},"Tags Per Pop":{"value":0.7660238503477373,"rank":333},"Grabs":{"value":43114,"rank":128},"Grabs Per Game":{"value":0.8306008823472749,"rank":151},"Grabs Per Hour":{"value":77.89113836895243,"rank":61},"Captures":{"value":5538,"rank":126},"Captures Per Game":{"value":0.7253438113948919,"rank":146},"Captures Per Hour":{"value":10.005128827927322,"rank":132},"Captures Per Grab":{"value":0.1284501554019576,"rank":204},"Hold":{"value":373679,"rank":138},"Hold Per Game":{"value":48.942894564505565,"rank":154},"Hold Per Grab":{"value":8.667231061836063,"rank":249},"Hold Per Hour":{"value":675.1004939131552,"rank":134},"Hold Per Cap":{"value":67.47544239797762,"rank":285},"Prevent":{"value":130038,"rank":241},"Prevent Per Game":{"value":17.03182711198428,"rank":401},"Prevent Per Hour":{"value":234.93083108089795,"rank":405},"Returns":{"value":26006,"rank":200},"Returns Per Game":{"value":3.406155861165684,"rank":378},"Returns Per Hour":{"value":46.98327560474502,"rank":377},"Support":{"value":81023,"rank":185},"Support Per Game":{"value":10.612049770792403,"rank":349},"Support Per Hour":{"value":146.37875641479872,"rank":348},"Non-Return Tags":{"value":13756,"rank":101},"Prevent Per Return":{"value":5.000307621318157,"rank":363},"Power-up Percent":{"value":0.24,"rank":29},"Time Played":{"value":1992658,"rank":163},"Disconnects":{"value":778,"rank":52},"Disconnects Per Game":{"value":0.10189914865749836,"rank":41}}},"Rolling 300":{"All":{"Win Percent":{"value":0.5188039457459925,"rank":292},"Points":{"value":5285,"rank":373},"Points Per Game":{"value":17.616666666666667,"rank":375},"Games":{"value":300,"rank":269},"Games Per Hour":{"value":13.965577437833785,"rank":86},"Wins":{"value":153,"rank":316},"Ties":{"value":2,"rank":270},"Losses":{"value":120,"rank":108},"Saves":{"value":4,"rank":186},"Save Percent":{"value":0.44,"rank":142},"Tags":{"value":1678,"rank":343},"Tags Per Game":{"value":5.593333333333334,"rank":345},"Tags Per Hour":{"value":78.11412980228363,"rank":306},"Popped":{"value":2022,"rank":105},"Popped Per Game":{"value":6.74,"rank":108},"Popped Per Hour":{"value":94.1279919309997,"rank":49},"Tags Per Pop":{"value":0.8298714144411474,"rank":354},"Grabs":{"value":1683,"rank":167},"Grabs Per Game":{"value":0.8323442136498517,"rank":265},"Grabs Per Hour":{"value":78.34688942624753,"rank":95},"Captures":{"value":190,"rank":252},"Captures Per Game":{"value":0.6333333333333333,"rank":252},"Captures Per Hour":{"value":8.844865710628063,"rank":230},"Captures Per Grab":{"value":0.11289364230540701,"rank":262},"Hold":{"value":12944,"rank":275},"Hold Per Game":{"value":43.14666666666667,"rank":276},"Hold Per Grab":{"value":7.691027926322044,"rank":311},"Hold Per Hour":{"value":602.568114517735,"rank":243},"Hold Per Cap":{"value":68.12631578947368,"rank":219},"Prevent":{"value":6719,"rank":381},"Prevent Per Game":{"value":22.39666666666667,"rank":387},"Prevent Per Hour":{"value":312.782382682684,"rank":379},"Returns":{"value":1150,"rank":386},"Returns Per Game":{"value":3.8333333333333335,"rank":390},"Returns Per Hour":{"value":53.53471351169617,"rank":365},"Support":{"value":3879,"rank":346},"Support Per Game":{"value":12.93,"rank":351},"Support Per Hour":{"value":180.57491627119083,"rank":341},"Non-Return Tags":{"value":528,"rank":98},"Prevent Per Return":{"value":5.842608695652174,"rank":264},"Power-up Percent":{"value":0.2,"rank":88},"Time Played":{"value":77333,"rank":341},"Disconnects":{"value":21,"rank":58},"Disconnects Per Game":{"value":0.07,"rank":59}},"CTF":{"Win Percent":{"value":0.5358851674641149,"rank":283},"Points":{"value":3724,"rank":365},"Points Per Game":{"value":17.483568075117372,"rank":383},"Games":{"value":213,"rank":166},"Games Per Hour":{"value":13.974849644614544,"rank":64},"Wins":{"value":112,"rank":282},"Ties":{"value":2,"rank":218},"Losses":{"value":82,"rank":95},"Saves":{"value":4,"rank":116},"Save Percent":{"value":0.5,"rank":128},"Tags":{"value":1108,"rank":337},"Tags Per Game":{"value":5.2018779342723,"rank":358},"Tags Per Hour":{"value":72.69546200109349,"rank":306},"Popped":{"value":1381,"rank":84},"Popped Per Game":{"value":6.483568075117371,"rank":98},"Popped Per Hour":{"value":90.6068890103882,"rank":46},"Tags Per Pop":{"value":0.8023171614771905,"rank":360},"Grabs":{"value":1148,"rank":112},"Grabs Per Game":{"value":0.8312816799420709,"rank":219},"Grabs Per Hour":{"value":75.31984691088026,"rank":61},"Captures":{"value":139,"rank":203},"Captures Per Game":{"value":0.6525821596244131,"rank":213},"Captures Per Hour":{"value":9.119737561509021,"rank":186},"Captures Per Grab":{"value":0.1210801393728223,"rank":253},"Hold":{"value":10080,"rank":241},"Hold Per Game":{"value":47.32394366197183,"rank":255},"Hold Per Grab":{"value":8.78048780487805,"rank":356},"Hold Per Hour":{"value":661.3449972662658,"rank":219},"Hold Per Cap":{"value":72.5179856115108,"rank":276},"Prevent":{"value":1679,"rank":411},"Prevent Per Game":{"value":7.882629107981221,"rank":417},"Prevent Per Hour":{"value":110.15855658829962,"rank":413},"Returns":{"value":725,"rank":384},"Returns Per Game":{"value":3.403755868544601,"rank":391},"Returns Per Hour":{"value":47.566976489885185,"rank":368},"Support":{"value":2094,"rank":240},"Support Per Game":{"value":9.830985915492958,"rank":250},"Support Per Hour":{"value":137.38655002733734,"rank":172},"Non-Return Tags":{"value":383,"rank":112},"Prevent Per Return":{"value":2.3158620689655174,"rank":411},"Power-up Percent":{"value":0.18,"rank":129},"Time Played":{"value":54870,"rank":325},"Disconnects":{"value":13,"rank":71},"Disconnects Per Game":{"value":0.06103286384976526,"rank":76}},"Neutral":{"Win Percent":{"value":0,"rank":359},"Points":{"value":1561,"rank":299},"Points Per Game":{"value":17.942528735632184,"rank":295},"Games":{"value":87,"rank":261},"Games Per Hour":{"value":13.942928371099141,"rank":211},"Wins":{"value":41,"rank":371},"Ties":{"value":0,"rank":342},"Losses":{"value":38,"rank":117},"Saves":{"value":0,"rank":359},"Save Percent":{"value":0,"rank":359},"Tags":{"value":570,"rank":274},"Tags Per Game":{"value":6.551724137931035,"rank":266},"Tags Per Hour":{"value":91.35022036237368,"rank":275},"Popped":{"value":641,"rank":253},"Popped Per Game":{"value":7.367816091954023,"rank":222},"Popped Per Hour":{"value":102.72893202154654,"rank":223},"Tags Per Pop":{"value":0.8892355694227769,"rank":286},"Grabs":{"value":535,"rank":292},"Grabs Per Game":{"value":0.8346333853354134,"rank":332},"Grabs Per Hour":{"value":85.74099630503494,"rank":310},"Captures":{"value":51,"rank":321},"Captures Per Game":{"value":0.5862068965517241,"rank":304},"Captures Per Hour":{"value":8.173440769265014,"rank":298},"Captures Per Grab":{"value":0.09532710280373832,"rank":286},"Hold":{"value":2864,"rank":301},"Hold Per Game":{"value":32.91954022988506,"rank":308},"Hold Per Grab":{"value":5.353271028037383,"rank":274},"Hold Per Hour":{"value":458.99479143480386,"rank":303},"Hold Per Cap":{"value":56.15686274509804,"rank":150},"Prevent":{"value":5040,"rank":230},"Prevent Per Game":{"value":57.93103448275862,"rank":199},"Prevent Per Hour":{"value":807.7282642567778,"rank":193},"Returns":{"value":425,"rank":307},"Returns Per Game":{"value":4.885057471264368,"rank":329},"Returns Per Hour":{"value":68.11200641054178,"rank":346},"Support":{"value":1785,"rank":363},"Support Per Game":{"value":20.517241379310345,"rank":399},"Support Per Hour":{"value":286.07042692427547,"rank":419},"Non-Return Tags":{"value":145,"rank":106},"Prevent Per Return":{"value":11.858823529411765,"rank":125},"Power-up Percent":{"value":0.27,"rank":36},"Time Played":{"value":22463,"rank":265},"Disconnects":{"value":8,"rank":28},"Disconnects Per Game":{"value":0.09195402298850575,"rank":28}}}}
