{"name":"Paige","id":294,"All Time":{"Daily":{"Win Percent":{"value":0,"rank":83},"Points":{"value":0,"rank":202},"Points Per Game":{"value":0,"rank":202},"Games":{"value":0,"rank":203},"Games Per Hour":{"value":0,"rank":203},"Wins":{"value":0,"rank":193},"Ties":{"value":0,"rank":85},"Losses":{"value":0,"rank":189},"Saves":{"value":0,"rank":83},"Save Percent":{"value":0,"rank":83},"Tags":{"value":0,"rank":203},"Tags Per Game":{"value":0,"rank":203},"Tags Per Hour":{"value":0,"rank":203},"Popped":{"value":0,"rank":202},"Popped Per Game":{"value":0,"rank":202},"Popped Per Hour":{"value":0,"rank":202},"Tags Per Pop":{"value":0,"rank":203},"Grabs":{"value":0,"rank":201},"Grabs Per Game":{"value":0,"rank":201},"Grabs Per Hour":{"value":0,"rank":201},"Captures":{"value":0,"rank":189},"Captures Per Game":{"value":0,"rank":189},"Captures Per Hour":{"value":0,"rank":189},"Captures Per Grab":{"value":0,"rank":189},"Hold":{"value":0,"rank":201},"Hold Per Game":{"value":0,"rank":201},"Hold Per Grab":{"value":0,"rank":201},"Hold Per Hour":{"value":0,"rank":201},"Hold Per Cap":{"value":0,"rank":201},"Prevent":{"value":0,"rank":203},"Prevent Per Game":{"value":0,"rank":203},"Prevent Per Hour":{"value":0,"rank":203},"Returns":{"value":0,"rank":203},"Returns Per Game":{"value":0,"rank":203},"Returns Per Hour":{"value":0,"rank":203},"Support":{"value":0,"rank":202},"Support Per Game":{"value":0,"rank":202},"Support Per Hour":{"value":0,"rank":202},"Non-Return Tags":{"value":0,"rank":192},"Prevent Per Return":{"value":0,"rank":203},"Power-up Percent":{"value":0,"rank":194},"Time Played":{"value":0,"rank":203},"Disconnects":{"value":0,"rank":115},"Disconnects Per Game":{"value":0,"rank":115}},"Weekly":{"Win Percent":{"value":0,"rank":186},"Points":{"value":0,"rank":285},"Points Per Game":{"value":0,"rank":285},"Games":{"value":0,"rank":285},"Games Per Hour":{"value":0,"rank":285},"Wins":{"value":0,"rank":284},"Ties":{"value":0,"rank":198},"Losses":{"value":0,"rank":283},"Saves":{"value":0,"rank":186},"Save Percent":{"value":0,"rank":186},"Tags":{"value":0,"rank":285},"Tags Per Game":{"value":0,"rank":285},"Tags Per Hour":{"value":0,"rank":285},"Popped":{"value":0,"rank":285},"Popped Per Game":{"value":0,"rank":285},"Popped Per Hour":{"value":0,"rank":285},"Tags Per Pop":{"value":0,"rank":285},"Grabs":{"value":0,"rank":285},"Grabs Per Game":{"value":0,"rank":285},"Grabs Per Hour":{"value":0,"rank":285},"Captures":{"value":0,"rank":284},"Captures Per Game":{"value":0,"rank":284},"Captures Per Hour":{"value":0,"rank":284},"Captures Per Grab":{"value":0,"rank":284},"Hold":{"value":0,"rank":285},"Hold Per Game":{"value":0,"rank":285},"Hold Per Grab":{"value":0,"rank":285},"Hold Per Hour":{"value":0,"rank":285},"Hold Per Cap":{"value":0,"rank":285},"Prevent":{"value":0,"rank":284},"Prevent Per Game":{"value":0,"rank":284},"Prevent Per Hour":{"value":0,"rank":284},"Returns":{"value":0,"rank":285},"Returns Per Game":{"value":0,"rank":285},"Returns Per Hour":{"value":0,"rank":285},"Support":{"value":0,"rank":284},"Support Per Game":{"value":0,"rank":284},"Support Per Hour":{"value":0,"rank":284},"Non-Return Tags":{"value":0,"rank":283},"Prevent Per Return":{"value":0,"rank":284},"Power-up Percent":{"value":0,"rank":285},"Time Played":{"value":0,"rank":285},"Disconnects":{"value":0,"rank":227},"Disconnects Per Game":{"value":0,"rank":227}},"Monthly":{"Win Percent":{"value":0,"rank":276},"Points":{"value":0,"rank":305},"Points Per Game":{"value":0,"rank":305},"Games":{"value":0,"rank":306},"Games Per Hour":{"value":0,"rank":306},"Wins":{"value":0,"rank":304},"Ties":{"value":0,"rank":271},"Losses":{"value":0,"rank":301},"Saves":{"value":0,"rank":276},"Save Percent":{"value":0,"rank":276},"Tags":{"value":0,"rank":306},"Tags Per Game":{"value":0,"rank":306},"Tags Per Hour":{"value":0,"rank":306},"Popped":{"value":0,"rank":306},"Popped Per Game":{"value":0,"rank":306},"Popped Per Hour":{"value":0,"rank":306},"Tags Per Pop":{"value":0,"rank":306},"Grabs":{"value":0,"rank":306},"Grabs Per Game":{"value":0,"rank":306},"Grabs Per Hour":{"value":0,"rank":306},"Captures":{"value":0,"rank":303},"Captures Per Game":{"value":0,"rank":303},"Captures Per Hour":{"value":0,"rank":303},"Captures Per Grab":{"value":0,"rank":303},"Hold":{"value":0,"rank":306},"Hold Per Game":{"value":0,"rank":306},"Hold Per Grab":{"value":0,"rank":306},"Hold Per Hour":{"value":0,"rank":306},"Hold Per Cap":{"value":0,"rank":306},"Prevent":{"value":0,"rank":306},"Prevent Per Game":{"value":0,"rank":306},"Prevent Per Hour":{"value":0,"rank":306},"Returns":{"value":0,"rank":306},"Returns Per Game":{"value":0,"rank":306},"Returns Per Hour":{"value":0,"rank":306},"Support":{"value":0,"rank":306},"Support Per Game":{"value":0,"rank":306},"Support Per Hour":{"value":0,"rank":306},"Non-Return Tags":{"value":0,"rank":305},"Prevent Per Return":{"value":0,"rank":306},"Power-up Percent":{"value":0,"rank":306},"Time Played":{"value":0,"rank":306},"Disconnects":{"value":0,"rank":272},"Disconnects Per Game":{"value":0,"rank":272}},"All":{"Win Percent":{"value":0.7718120805369127,"rank":17},"Points":{"value":6301,"rank":418},"Points Per Game":{"value":20.93355481727575,"rank":66},"Games":{"value":301,"rank":418},"Games Per Hour":{"value":14.455902560066171,"rank":51},"Wins":{"value":230,"rank":414},"Ties":{"value":1,"rank":398},"Losses":{"value":66,"rank":416},"Saves":{"value":9,"rank":321},"Save Percent":{"value":0.75,"rank":7},"Tags":{"value":2309,"rank":407},"Tags Per Game":{"value":7.67109634551495,"rank":31},"Tags Per Hour":{"value":110.8926212996438,"rank":14},"Popped":{"value":1572,"rank":422},"Popped Per Game":{"value":5.222591362126246,"rank":373},"Popped Per Hour":{"value":75.49727184194026,"rank":334},"Tags Per Pop":{"value":1.4688295165394403,"rank":17},"Grabs":{"value":1522,"rank":416},"Grabs Per Game":{"value":0.9681933842239185,"rank":17},"Grabs Per Hour":{"value":73.0959591243213,"rank":112},"Captures":{"value":295,"rank":403},"Captures Per Game":{"value":0.9800664451827242,"rank":39},"Captures Per Hour":{"value":14.167745033951892,"rank":30},"Captures Per Grab":{"value":0.1938239159001314,"rank":33},"Hold":{"value":16927,"rank":411},"Hold Per Game":{"value":56.2358803986711,"rank":82},"Hold Per Grab":{"value":11.121550591327201,"rank":52},"Hold Per Hour":{"value":812.9404074227244,"rank":50},"Hold Per Cap":{"value":57.37966101694915,"rank":391},"Prevent":{"value":8377,"rank":417},"Prevent Per Game":{"value":27.830564784053156,"rank":259},"Prevent Per Hour":{"value":402.3159327098814,"rank":215},"Returns":{"value":1772,"rank":407},"Returns Per Game":{"value":5.887043189368771,"rank":39},"Returns Per Hour":{"value":85.10252271241612,"rank":20},"Support":{"value":3589,"rank":418},"Support Per Game":{"value":11.92358803986711,"rank":286},"Support Per Hour":{"value":172.36622687068933,"rank":242},"Non-Return Tags":{"value":537,"rank":401},"Prevent Per Return":{"value":4.727426636568849,"rank":390},"Power-up Percent":{"value":0.27,"rank":6},"Time Played":{"value":74959,"rank":422},"Disconnects":{"value":1,"rank":417},"Disconnects Per Game":{"value":0.0033222591362126247,"rank":415}}},"Rolling 300":{"All":{"Win Percent":{"value":0.7744107744107744,"rank":54},"Points":{"value":6276,"rank":203},"Points Per Game":{"value":20.92,"rank":203},"Games":{"value":300,"rank":66},"Games Per Hour":{"value":14.493531590530893,"rank":49},"Wins":{"value":230,"rank":48},"Ties":{"value":1,"rank":310},"Losses":{"value":65,"rank":345},"Saves":{"value":9,"rank":21},"Save Percent":{"value":0.75,"rank":11},"Tags":{"value":2301,"rank":94},"Tags Per Game":{"value":7.67,"rank":94},"Tags Per Hour":{"value":111.16538729937194,"rank":37},"Popped":{"value":1559,"rank":390},"Popped Per Game":{"value":5.196666666666666,"rank":396},"Popped Per Hour":{"value":75.31805249879221,"rank":351},"Tags Per Pop":{"value":1.4759461193072483,"rank":34},"Grabs":{"value":1512,"rank":300},"Grabs Per Game":{"value":0.9698524695317511,"rank":43},"Grabs Per Hour":{"value":73.0473992162757,"rank":197},"Captures":{"value":295,"rank":75},"Captures Per Game":{"value":0.9833333333333333,"rank":75},"Captures Per Hour":{"value":14.251972730688712,"rank":54},"Captures Per Grab":{"value":0.19510582010582012,"rank":35},"Hold":{"value":16872,"rank":119},"Hold Per Game":{"value":56.24,"rank":119},"Hold Per Grab":{"value":11.158730158730158,"rank":48},"Hold Per Hour":{"value":815.1162166514574,"rank":69},"Hold Per Cap":{"value":57.19322033898305,"rank":350},"Prevent":{"value":8345,"rank":305},"Prevent Per Game":{"value":27.816666666666666,"rank":311},"Prevent Per Hour":{"value":403.161737076601,"rank":259},"Returns":{"value":1764,"rank":109},"Returns Per Game":{"value":5.88,"rank":109},"Returns Per Hour":{"value":85.22196575232165,"rank":60},"Support":{"value":3563,"rank":386},"Support Per Game":{"value":11.876666666666667,"rank":392},"Support Per Hour":{"value":172.1348435235386,"rank":365},"Non-Return Tags":{"value":537,"rank":90},"Prevent Per Return":{"value":4.730725623582766,"rank":380},"Power-up Percent":{"value":0.27,"rank":8},"Time Played":{"value":74516,"rank":379},"Disconnects":{"value":1,"rank":329},"Disconnects Per Game":{"value":0.0033333333333333335,"rank":330}},"CTF":{"Win Percent":{"value":0.7691415313225058,"rank":70},"Points":{"value":4700,"rank":139},"Points Per Game":{"value":21.076233183856502,"rank":238},"Games":{"value":223,"rank":77},"Games Per Hour":{"value":14.39328743545611,"rank":42},"Wins":{"value":170,"rank":58},"Ties":{"value":0,"rank":370},"Losses":{"value":50,"rank":277},"Saves":{"value":7,"rank":14},"Save Percent":{"value":0.78,"rank":15},"Tags":{"value":1753,"rank":55},"Tags Per Game":{"value":7.860986547085202,"rank":79},"Tags Per Hour":{"value":113.14543889845093,"rank":31},"Popped":{"value":1066,"rank":317},"Popped Per Game":{"value":4.780269058295964,"rank":367},"Popped Per Hour":{"value":68.80378657487091,"rank":300},"Tags Per Pop":{"value":1.6444652908067543,"rank":51},"Grabs":{"value":982,"rank":236},"Grabs Per Game":{"value":0.9212007504690432,"rank":76},"Grabs Per Hour":{"value":63.38209982788296,"rank":202},"Captures":{"value":197,"rank":85},"Captures Per Game":{"value":0.8834080717488789,"rank":103},"Captures Per Hour":{"value":12.71514629948365,"rank":67},"Captures Per Grab":{"value":0.20061099796334012,"rank":42},"Hold":{"value":12709,"rank":117},"Hold Per Game":{"value":56.99103139013453,"rank":148},"Hold Per Grab":{"value":12.941955193482688,"rank":65},"Hold Per Hour":{"value":820.2882960413081,"rank":93},"Hold Per Cap":{"value":64.51269035532995,"rank":357},"Prevent":{"value":4814,"rank":186},"Prevent Per Game":{"value":21.58744394618834,"rank":223},"Prevent Per Hour":{"value":310.7142857142857,"rank":173},"Returns":{"value":1354,"rank":60},"Returns Per Game":{"value":6.071748878923767,"rank":84},"Returns Per Hour":{"value":87.39242685025818,"rank":43},"Support":{"value":1903,"rank":327},"Support Per Game":{"value":8.533632286995516,"rank":366},"Support Per Hour":{"value":122.82702237521514,"rank":295},"Non-Return Tags":{"value":399,"rank":92},"Prevent Per Return":{"value":3.5553914327917284,"rank":302},"Power-up Percent":{"value":0.24,"rank":21},"Time Played":{"value":55776,"rank":298},"Disconnects":{"value":1,"rank":304},"Disconnects Per Game":{"value":0.004484304932735426,"rank":345}},"Neutral":{"Win Percent":{"value":0.7893186726880032,"rank":47},"Points":{"value":1576,"rank":290},"Points Per Game":{"value":20.467532467532468,"rank":133},"Games":{"value":77,"rank":346},"Games Per Hour":{"value":14.79188900747065,"rank":121},"Wins":{"value":60,"rank":156},"Ties":{"value":1,"rank":86},"Losses":{"value":15,"rank":363},"Saves":{"value":2,"rank":54},"Save Percent":{"value":0.67,"rank":70},"Tags":{"value":548,"rank":293},"Tags Per Game":{"value":7.116883116883117,"rank":180},"Tags Per Hour":{"value":105.27214514407684,"rank":110},"Popped":{"value":493,"rank":367},"Popped Per Game":{"value":6.402597402597403,"rank":366},"Popped Per Hour":{"value":94.70651013874065,"rank":359},"Tags Per Pop":{"value":1.1115618661257607,"rank":17},"Grabs":{"value":530,"rank":295},"Grabs Per Game":{"value":1.075050709939148,"rank":7},"Grabs Per Hour":{"value":101.81430096051227,"rank":124},"Captures":{"value":98,"rank":77},"Captures Per Game":{"value":1.2727272727272727,"rank":30},"Captures Per Hour":{"value":18.82604055496265,"rank":33},"Captures Per Grab":{"value":0.18490566037735848,"rank":27},"Hold":{"value":4163,"rank":116},"Hold Per Game":{"value":54.064935064935064,"rank":47},"Hold Per Grab":{"value":7.854716981132076,"rank":17},"Hold Per Hour":{"value":799.7225186766276,"rank":19},"Hold Per Cap":{"value":42.47959183673469,"rank":313},"Prevent":{"value":3531,"rank":371},"Prevent Per Game":{"value":45.857142857142854,"rank":365},"Prevent Per Hour":{"value":678.3137673425827,"rank":361},"Returns":{"value":410,"rank":318},"Returns Per Game":{"value":5.324675324675325,"rank":254},"Returns Per Hour":{"value":78.76200640341516,"rank":194},"Support":{"value":1660,"rank":376},"Support Per Game":{"value":21.558441558441558,"rank":383},"Support Per Hour":{"value":318.8900747065102,"rank":381},"Non-Return Tags":{"value":138,"rank":121},"Prevent Per Return":{"value":8.612195121951219,"rank":303},"Power-up Percent":{"value":0.4,"rank":2},"Time Played":{"value":18740,"rank":352},"Disconnects":{"value":0,"rank":283},"Disconnects Per Game":{"value":0,"rank":283}}}}
