{"name":"aIchemist","id":352,"All Time":{"Daily":{"Win Percent":{"value":0,"rank":326},"Points":{"value":0,"rank":359},"Points Per Game":{"value":0,"rank":359},"Games":{"value":0,"rank":359},"Games Per Hour":{"value":0,"rank":359},"Wins":{"value":0,"rank":355},"Ties":{"value":0,"rank":322},"Losses":{"value":0,"rank":356},"Saves":{"value":0,"rank":326},"Save Percent":{"value":0,"rank":326},"Tags":{"value":0,"rank":359},"Tags Per Game":{"value":0,"rank":359},"Tags Per Hour":{"value":0,"rank":359},"Popped":{"value":0,"rank":358},"Popped Per Game":{"value":0,"rank":358},"Popped Per Hour":{"value":0,"rank":358},"Tags Per Pop":{"value":0,"rank":359},"Grabs":{"value":0,"rank":358},"Grabs Per Game":{"value":0,"rank":358},"Grabs Per Hour":{"value":0,"rank":358},"Captures":{"value":0,"rank":356},"Captures Per Game":{"value":0,"rank":356},"Captures Per Hour":{"value":0,"rank":356},"Captures Per Grab":{"value":0,"rank":356},"Hold":{"value":0,"rank":358},"Hold Per Game":{"value":0,"rank":358},"Hold Per Grab":{"value":0,"rank":358},"Hold Per Hour":{"value":0,"rank":358},"Hold Per Cap":{"value":0,"rank":358},"Prevent":{"value":0,"rank":359},"Prevent Per Game":{"value":0,"rank":359},"Prevent Per Hour":{"value":0,"rank":359},"Returns":{"value":0,"rank":359},"Returns Per Game":{"value":0,"rank":359},"Returns Per Hour":{"value":0,"rank":359},"Support":{"value":0,"rank":358},"Support Per Game":{"value":0,"rank":358},"Support Per Hour":{"value":0,"rank":358},"Non-Return Tags":{"value":0,"rank":355},"Prevent Per Return":{"value":0,"rank":359},"Power-up Percent":{"value":0,"rank":357},"Time Played":{"value":0,"rank":359},"Disconnects":{"value":0,"rank":331},"Disconnects Per Game":{"value":0,"rank":331}},"Weekly":{"Win Percent":{"value":0,"rank":362},"Points":{"value":0,"rank":389},"Points Per Game":{"value":0,"rank":389},"Games":{"value":0,"rank":389},"Games Per Hour":{"value":0,"rank":389},"Wins":{"value":0,"rank":388},"Ties":{"value":0,"rank":360},"Losses":{"value":0,"rank":388},"Saves":{"value":0,"rank":362},"Save Percent":{"value":0,"rank":362},"Tags":{"value":0,"rank":389},"Tags Per Game":{"value":0,"rank":389},"Tags Per Hour":{"value":0,"rank":389},"Popped":{"value":0,"rank":389},"Popped Per Game":{"value":0,"rank":389},"Popped Per Hour":{"value":0,"rank":389},"Tags Per Pop":{"value":0,"rank":389},"Grabs":{"value":0,"rank":389},"Grabs Per Game":{"value":0,"rank":389},"Grabs Per Hour":{"value":0,"rank":389},"Captures":{"value":0,"rank":388},"Captures Per Game":{"value":0,"rank":388},"Captures Per Hour":{"value":0,"rank":388},"Captures Per Grab":{"value":0,"rank":388},"Hold":{"value":0,"rank":389},"Hold Per Game":{"value":0,"rank":389},"Hold Per Grab":{"value":0,"rank":389},"Hold Per Hour":{"value":0,"rank":389},"Hold Per Cap":{"value":0,"rank":389},"Prevent":{"value":0,"rank":388},"Prevent Per Game":{"value":0,"rank":388},"Prevent Per Hour":{"value":0,"rank":388},"Returns":{"value":0,"rank":389},"Returns Per Game":{"value":0,"rank":389},"Returns Per Hour":{"value":0,"rank":389},"Support":{"value":0,"rank":388},"Support Per Game":{"value":0,"rank":388},"Support Per Hour":{"value":0,"rank":388},"Non-Return Tags":{"value":0,"rank":388},"Prevent Per Return":{"value":0,"rank":388},"Power-up Percent":{"value":0,"rank":389},"Time Played":{"value":0,"rank":389},"Disconnects":{"value":0,"rank":373},"Disconnects Per Game":{"value":0,"rank":373}},"Monthly":{"Win Percent":{"value":0,"rank":388},"Points":{"value":119,"rank":269},"Points Per Game":{"value":17,"rank":225},"Games":{"value":7,"rank":269},"Games Per Hour":{"value":13.333333333333334,"rank":104},"Wins":{"value":3,"rank":270},"Ties":{"value":0,"rank":384},"Losses":{"value":3,"rank":265},"Saves":{"value":0,"rank":388},"Save Percent":{"value":0,"rank":388},"Tags":{"value":55,"rank":269},"Tags Per Game":{"value":7.857142857142857,"rank":42},"Tags Per Hour":{"value":104.76190476190476,"rank":33},"Popped":{"value":64,"rank":266},"Popped Per Game":{"value":9.142857142857142,"rank":1},"Popped Per Hour":{"value":121.90476190476191,"rank":1},"Tags Per Pop":{"value":0.859375,"rank":187},"Grabs":{"value":50,"rank":267},"Grabs Per Game":{"value":0.78125,"rank":184},"Grabs Per Hour":{"value":95.23809523809523,"rank":5},"Captures":{"value":5,"rank":267},"Captures Per Game":{"value":0.7142857142857143,"rank":75},"Captures Per Hour":{"value":9.523809523809524,"rank":65},"Captures Per Grab":{"value":0.1,"rank":128},"Hold":{"value":357,"rank":266},"Hold Per Game":{"value":51,"rank":59},"Hold Per Grab":{"value":7.14,"rank":197},"Hold Per Hour":{"value":680,"rank":55},"Hold Per Cap":{"value":71.4,"rank":182},"Prevent":{"value":148,"rank":270},"Prevent Per Game":{"value":21.142857142857142,"rank":268},"Prevent Per Hour":{"value":281.9047619047619,"rank":269},"Returns":{"value":47,"rank":269},"Returns Per Game":{"value":6.714285714285714,"rank":28},"Returns Per Hour":{"value":89.52380952380953,"rank":25},"Support":{"value":94,"rank":268},"Support Per Game":{"value":13.428571428571429,"rank":252},"Support Per Hour":{"value":179.04761904761907,"rank":259},"Non-Return Tags":{"value":8,"rank":270},"Prevent Per Return":{"value":3.148936170212766,"rank":271},"Power-up Percent":{"value":0.29,"rank":2},"Time Played":{"value":1890,"rank":269},"Disconnects":{"value":1,"rank":225},"Disconnects Per Game":{"value":0.14285714285714285,"rank":17}},"All":{"Win Percent":{"value":0.6908804039129063,"rank":86},"Points":{"value":15914,"rank":362},"Points Per Game":{"value":20.32439335887612,"rank":97},"Games":{"value":783,"rank":365},"Games Per Hour":{"value":13.256581731990181,"rank":232},"Wins":{"value":534,"rank":357},"Ties":{"value":11,"rank":292},"Losses":{"value":205,"rank":365},"Saves":{"value":7,"rank":351},"Save Percent":{"value":0.41,"rank":122},"Tags":{"value":5352,"rank":358},"Tags Per Game":{"value":6.835249042145594,"rank":72},"Tags Per Hour":{"value":90.61203758571067,"rank":66},"Popped":{"value":4763,"rank":364},"Popped Per Game":{"value":6.08301404853129,"rank":231},"Popped Per Hour":{"value":80.63997291119952,"rank":239},"Tags Per Pop":{"value":1.1236615578416964,"rank":100},"Grabs":{"value":4224,"rank":361},"Grabs Per Game":{"value":0.8868360277136259,"rank":74},"Grabs Per Hour":{"value":71.51443325150258,"rank":129},"Captures":{"value":699,"rank":329},"Captures Per Game":{"value":0.89272030651341,"rank":66},"Captures Per Hour":{"value":11.834419707102345,"rank":75},"Captures Per Grab":{"value":0.16548295454545456,"rank":73},"Hold":{"value":43016,"rank":352},"Hold Per Game":{"value":54.93742017879949,"rank":98},"Hold Per Grab":{"value":10.183712121212121,"rank":113},"Hold Per Hour":{"value":728.2824007449419,"rank":101},"Hold Per Cap":{"value":61.53934191702432,"rank":350},"Prevent":{"value":25814,"rank":355},"Prevent Per Game":{"value":32.96807151979566,"rank":162},"Prevent Per Hour":{"value":437.0439346482689,"rank":158},"Returns":{"value":4218,"rank":357},"Returns Per Game":{"value":5.3869731800766285,"rank":76},"Returns Per Hour":{"value":71.41285024972488,"rank":73},"Support":{"value":9815,"rank":369},"Support Per Game":{"value":12.535121328224777,"rank":253},"Support Per Hour":{"value":166.17286040802506,"rank":267},"Non-Return Tags":{"value":1134,"rank":352},"Prevent Per Return":{"value":6.119962067330488,"rank":269},"Power-up Percent":{"value":0.26,"rank":13},"Time Played":{"value":212634,"rank":363},"Disconnects":{"value":23,"rank":343},"Disconnects Per Game":{"value":0.02937420178799489,"rank":214}}},"Rolling 300":{"All":{"Win Percent":{"value":0.7519331889885554,"rank":107},"Points":{"value":6286,"rank":200},"Points Per Game":{"value":20.953333333333333,"rank":200},"Games":{"value":300,"rank":314},"Games Per Hour":{"value":13.184881336067976,"rank":200},"Wins":{"value":221,"rank":132},"Ties":{"value":5,"rank":67},"Losses":{"value":62,"rank":364},"Saves":{"value":3,"rank":263},"Save Percent":{"value":0.33,"rank":251},"Tags":{"value":2164,"rank":140},"Tags Per Game":{"value":7.213333333333333,"rank":140},"Tags Per Hour":{"value":95.10694403750367,"rank":142},"Popped":{"value":1768,"rank":286},"Popped Per Game":{"value":5.8933333333333335,"rank":292},"Popped Per Hour":{"value":77.70290067389394,"rank":300},"Tags Per Pop":{"value":1.2239819004524888,"rank":126},"Grabs":{"value":1673,"rank":174},"Grabs Per Game":{"value":0.9462669683257918,"rank":80},"Grabs Per Hour":{"value":73.52768825080575,"rank":187},"Captures":{"value":285,"rank":92},"Captures Per Game":{"value":0.95,"rank":92},"Captures Per Hour":{"value":12.525637269264577,"rank":94},"Captures Per Grab":{"value":0.17035265989240886,"rank":87},"Hold":{"value":17544,"rank":95},"Hold Per Game":{"value":58.48,"rank":95},"Hold Per Grab":{"value":10.486551105797968,"rank":89},"Hold Per Hour":{"value":771.0518605332552,"rank":100},"Hold Per Cap":{"value":61.55789473684211,"rank":300},"Prevent":{"value":10697,"rank":162},"Prevent Per Game":{"value":35.656666666666666,"rank":166},"Prevent Per Hour":{"value":470.1289188397305,"rank":161},"Returns":{"value":1771,"rank":107},"Returns Per Game":{"value":5.903333333333333,"rank":107},"Returns Per Hour":{"value":77.83474948725461,"rank":111},"Support":{"value":4034,"rank":329},"Support Per Game":{"value":13.446666666666667,"rank":335},"Support Per Hour":{"value":177.2927043656607,"rank":350},"Non-Return Tags":{"value":393,"rank":263},"Prevent Per Return":{"value":6.040090344438171,"rank":246},"Power-up Percent":{"value":0.22,"rank":58},"Time Played":{"value":81912,"rank":228},"Disconnects":{"value":6,"rank":177},"Disconnects Per Game":{"value":0.02,"rank":177}},"CTF":{"Win Percent":{"value":0.7664002412909063,"rank":75},"Points":{"value":4463,"rank":208},"Points Per Game":{"value":21.770731707317072,"rank":175},"Games":{"value":205,"rank":265},"Games Per Hour":{"value":12.874638009839154,"rank":218},"Wins":{"value":154,"rank":154},"Ties":{"value":3,"rank":128},"Losses":{"value":39,"rank":386},"Saves":{"value":2,"rank":284},"Save Percent":{"value":0.33,"rank":247},"Tags":{"value":1511,"rank":139},"Tags Per Game":{"value":7.3707317073170735,"rank":120},"Tags Per Hour":{"value":94.89550259935103,"rank":125},"Popped":{"value":1058,"rank":322},"Popped Per Game":{"value":5.160975609756098,"rank":312},"Popped Per Hour":{"value":66.44569275321865,"rank":336},"Tags Per Pop":{"value":1.4281663516068053,"rank":104},"Grabs":{"value":988,"rank":233},"Grabs Per Game":{"value":0.9338374291115312,"rank":67},"Grabs Per Hour":{"value":62.04947489620041,"rank":219},"Captures":{"value":180,"rank":122},"Captures Per Game":{"value":0.8780487804878049,"rank":108},"Captures Per Hour":{"value":11.30456020376121,"rank":113},"Captures Per Grab":{"value":0.18218623481781376,"rank":88},"Hold":{"value":12832,"rank":113},"Hold Per Game":{"value":62.59512195121951,"rank":97},"Hold Per Grab":{"value":12.987854251012147,"rank":64},"Hold Per Hour":{"value":805.8895363036879,"rank":101},"Hold Per Cap":{"value":71.28888888888889,"rank":292},"Prevent":{"value":5344,"rank":149},"Prevent Per Game":{"value":26.068292682926828,"rank":144},"Prevent Per Hour":{"value":335.6198318272217,"rank":152},"Returns":{"value":1232,"rank":107},"Returns Per Game":{"value":6.009756097560976,"rank":90},"Returns Per Hour":{"value":77.37343428352116,"rank":96},"Support":{"value":1741,"rank":382},"Support Per Game":{"value":8.492682926829268,"rank":370},"Support Per Hour":{"value":109.34021841526813,"rank":387},"Non-Return Tags":{"value":279,"rank":261},"Prevent Per Return":{"value":4.337662337662338,"rank":214},"Power-up Percent":{"value":0.22,"rank":54},"Time Played":{"value":57322,"rank":251},"Disconnects":{"value":5,"rank":174},"Disconnects Per Game":{"value":0.024390243902439025,"rank":161}},"Neutral":{"Win Percent":{"value":0.720664928292047,"rank":106},"Points":{"value":1823,"rank":167},"Points Per Game":{"value":19.189473684210526,"rank":227},"Games":{"value":95,"rank":166},"Games Per Hour":{"value":13.908092720618138,"rank":218},"Wins":{"value":67,"rank":95},"Ties":{"value":2,"rank":53},"Losses":{"value":23,"rank":243},"Saves":{"value":1,"rank":212},"Save Percent":{"value":0.33,"rank":204},"Tags":{"value":653,"rank":177},"Tags Per Game":{"value":6.873684210526315,"rank":214},"Tags Per Hour":{"value":95.59983733224888,"rank":222},"Popped":{"value":710,"rank":159},"Popped Per Game":{"value":7.473684210526316,"rank":199},"Popped Per Hour":{"value":103.94469296461976,"rank":193},"Tags Per Pop":{"value":0.9197183098591549,"rank":236},"Grabs":{"value":685,"rank":113},"Grabs Per Game":{"value":0.9647887323943662,"rank":135},"Grabs Per Hour":{"value":100.2846685644571,"rank":142},"Captures":{"value":105,"rank":59},"Captures Per Game":{"value":1.105263157894737,"rank":92},"Captures Per Hour":{"value":15.372102480683203,"rank":106},"Captures Per Grab":{"value":0.15328467153284672,"rank":91},"Hold":{"value":4712,"rank":68},"Hold Per Game":{"value":49.6,"rank":86},"Hold Per Grab":{"value":6.878832116788321,"rank":77},"Hold Per Hour":{"value":689.8413989426596,"rank":95},"Hold Per Cap":{"value":44.87619047619047,"rank":278},"Prevent":{"value":5353,"rank":192},"Prevent Per Game":{"value":56.34736842105263,"rank":229},"Prevent Per Hour":{"value":783.6844245628304,"rank":226},"Returns":{"value":539,"rank":164},"Returns Per Game":{"value":5.673684210526316,"rank":201},"Returns Per Hour":{"value":78.91012606750712,"rank":192},"Support":{"value":2293,"rank":280},"Support Per Game":{"value":24.13684210526316,"rank":333},"Support Per Hour":{"value":335.6974379829199,"rank":359},"Non-Return Tags":{"value":114,"rank":213},"Prevent Per Return":{"value":9.931354359925788,"rank":223},"Power-up Percent":{"value":0.23,"rank":89},"Time Played":{"value":24590,"rank":169},"Disconnects":{"value":1,"rank":221},"Disconnects Per Game":{"value":0.010526315789473684,"rank":204}}}}
