{"name":"Daffodil","id":389,"All Time":{"Daily":{"Win Percent":{"value":0,"rank":407},"Points":{"value":0,"rank":414},"Points Per Game":{"value":0,"rank":414},"Games":{"value":0,"rank":414},"Games Per Hour":{"value":0,"rank":414},"Wins":{"value":0,"rank":414},"Ties":{"value":0,"rank":404},"Losses":{"value":0,"rank":413},"Saves":{"value":0,"rank":407},"Save Percent":{"value":0,"rank":407},"Tags":{"value":0,"rank":414},"Tags Per Game":{"value":0,"rank":414},"Tags Per Hour":{"value":0,"rank":414},"Popped":{"value":0,"rank":414},"Popped Per Game":{"value":0,"rank":414},"Popped Per Hour":{"value":0,"rank":414},"Tags Per Pop":{"value":0,"rank":414},"Grabs":{"value":0,"rank":414},"Grabs Per Game":{"value":0,"rank":414},"Grabs Per Hour":{"value":0,"rank":414},"Captures":{"value":0,"rank":414},"Captures Per Game":{"value":0,"rank":414},"Captures Per Hour":{"value":0,"rank":414},"Captures Per Grab":{"value":0,"rank":414},"Hold":{"value":0,"rank":414},"Hold Per Game":{"value":0,"rank":414},"Hold Per Grab":{"value":0,"rank":414},"Hold Per Hour":{"value":0,"rank":414},"Hold Per Cap":{"value":0,"rank":414},"Prevent":{"value":0,"rank":414},"Prevent Per Game":{"value":0,"rank":414},"Prevent Per Hour":{"value":0,"rank":414},"Returns":{"value":0,"rank":414},"Returns Per Game":{"value":0,"rank":414},"Returns Per Hour":{"value":0,"rank":414},"Support":{"value":0,"rank":414},"Support Per Game":{"value":0,"rank":414},"Support Per Hour":{"value":0,"rank":414},"Non-Return Tags":{"value":0,"rank":413},"Prevent Per Return":{"value":0,"rank":414},"Power-up Percent":{"value":0,"rank":414},"Time Played":{"value":0,"rank":414},"Disconnects":{"value":0,"rank":407},"Disconnects Per Game":{"value":0,"rank":407}},"Weekly":{"Win Percent":{"value":0,"rank":416},"Points":{"value":0,"rank":423},"Points Per Game":{"value":0,"rank":423},"Games":{"value":0,"rank":423},"Games Per Hour":{"value":0,"rank":423},"Wins":{"value":0,"rank":423},"Ties":{"value":0,"rank":417},"Losses":{"value":0,"rank":422},"Saves":{"value":0,"rank":416},"Save Percent":{"value":0,"rank":416},"Tags":{"value":0,"rank":423},"Tags Per Game":{"value":0,"rank":423},"Tags Per Hour":{"value":0,"rank":423},"Popped":{"value":0,"rank":423},"Popped Per Game":{"value":0,"rank":423},"Popped Per Hour":{"value":0,"rank":423},"Tags Per Pop":{"value":0,"rank":423},"Grabs":{"value":0,"rank":423},"Grabs Per Game":{"value":0,"rank":423},"Grabs Per Hour":{"value":0,"rank":423},"Captures":{"value":0,"rank":423},"Captures Per Game":{"value":0,"rank":423},"Captures Per Hour":{"value":0,"rank":423},"Captures Per Grab":{"value":0,"rank":423},"Hold":{"value":0,"rank":423},"Hold Per Game":{"value":0,"rank":423},"Hold Per Grab":{"value":0,"rank":423},"Hold Per Hour":{"value":0,"rank":423},"Hold Per Cap":{"value":0,"rank":423},"Prevent":{"value":0,"rank":422},"Prevent Per Game":{"value":0,"rank":422},"Prevent Per Hour":{"value":0,"rank":422},"Returns":{"value":0,"rank":423},"Returns Per Game":{"value":0,"rank":423},"Returns Per Hour":{"value":0,"rank":423},"Support":{"value":0,"rank":422},"Support Per Game":{"value":0,"rank":422},"Support Per Hour":{"value":0,"rank":422},"Non-Return Tags":{"value":0,"rank":422},"Prevent Per Return":{"value":0,"rank":422},"Power-up Percent":{"value":0,"rank":423},"Time Played":{"value":0,"rank":423},"Disconnects":{"value":0,"rank":418},"Disconnects Per Game":{"value":0,"rank":418}},"Monthly":{"Win Percent":{"value":0,"rank":424},"Points":{"value":0,"rank":424},"Points Per Game":{"value":0,"rank":424},"Games":{"value":0,"rank":424},"Games Per Hour":{"value":0,"rank":424},"Wins":{"value":0,"rank":424},"Ties":{"value":0,"rank":421},"Losses":{"value":0,"rank":423},"Saves":{"value":0,"rank":424},"Save Percent":{"value":0,"rank":424},"Tags":{"value":0,"rank":424},"Tags Per Game":{"value":0,"rank":424},"Tags Per Hour":{"value":0,"rank":424},"Popped":{"value":0,"rank":424},"Popped Per Game":{"value":0,"rank":424},"Popped Per Hour":{"value":0,"rank":424},"Tags Per Pop":{"value":0,"rank":424},"Grabs":{"value":0,"rank":424},"Grabs Per Game":{"value":0,"rank":424},"Grabs Per Hour":{"value":0,"rank":424},"Captures":{"value":0,"rank":424},"Captures Per Game":{"value":0,"rank":424},"Captures Per Hour":{"value":0,"rank":424},"Captures Per Grab":{"value":0,"rank":424},"Hold":{"value":0,"rank":424},"Hold Per Game":{"value":0,"rank":424},"Hold Per Grab":{"value":0,"rank":424},"Hold Per Hour":{"value":0,"rank":424},"Hold Per Cap":{"value":0,"rank":424},"Prevent":{"value":0,"rank":424},"Prevent Per Game":{"value":0,"rank":424},"Prevent Per Hour":{"value":0,"rank":424},"Returns":{"value":0,"rank":424},"Returns Per Game":{"value":0,"rank":424},"Returns Per Hour":{"value":0,"rank":424},"Support":{"value":0,"rank":424},"Support Per Game":{"value":0,"rank":424},"Support Per Hour":{"value":0,"rank":424},"Non-Return Tags":{"value":0,"rank":424},"Prevent Per Return":{"value":0,"rank":424},"Power-up Percent":{"value":0,"rank":424},"Time Played":{"value":0,"rank":424},"Disconnects":{"value":0,"rank":423},"Disconnects Per Game":{"value":0,"rank":423}},"All":{"Win Percent":{"value":0.6810991243771468,"rank":98},"Points":{"value":10205,"rank":385},"Points Per Game":{"value":19.18233082706767,"rank":170},"Games":{"value":532,"rank":382},"Games Per Hour":{"value":14.226183844011143,"rank":69},"Wins":{"value":361,"rank":378},"Ties":{"value":8,"rank":312},"Losses":{"value":136,"rank":385},"Saves":{"value":7,"rank":355},"Save Percent":{"value":0.78,"rank":6},"Tags":{"value":3931,"rank":376},"Tags Per Game":{"value":7.389097744360902,"rank":40},"Tags Per Hour":{"value":105.11866295264625,"rank":24},"Popped":{"value":3091,"rank":383},"Popped Per Game":{"value":5.81015037593985,"rank":288},"Popped Per Hour":{"value":82.65626740947074,"rank":203},"Tags Per Pop":{"value":1.2717567130378518,"rank":52},"Grabs":{"value":2794,"rank":381},"Grabs Per Game":{"value":0.9039145907473309,"rank":58},"Grabs Per Hour":{"value":74.71420612813371,"rank":94},"Captures":{"value":460,"rank":364},"Captures Per Game":{"value":0.8646616541353384,"rank":79},"Captures Per Hour":{"value":12.300835654596101,"rank":59},"Captures Per Grab":{"value":0.164638511095204,"rank":76},"Hold":{"value":23319,"rank":389},"Hold Per Game":{"value":43.83270676691729,"rank":224},"Hold Per Grab":{"value":8.346098783106656,"rank":274},"Hold Per Hour":{"value":623.5721448467966,"rank":186},"Hold Per Cap":{"value":50.69347826086957,"rank":421},"Prevent":{"value":18395,"rank":374},"Prevent Per Game":{"value":34.57706766917293,"rank":139},"Prevent Per Hour":{"value":491.899721448468,"rank":90},"Returns":{"value":3314,"rank":375},"Returns Per Game":{"value":6.2293233082706765,"rank":24},"Returns Per Hour":{"value":88.61949860724235,"rank":14},"Support":{"value":7477,"rank":380},"Support Per Game":{"value":14.05451127819549,"rank":170},"Support Per Hour":{"value":199.94206128133703,"rank":96},"Non-Return Tags":{"value":617,"rank":393},"Prevent Per Return":{"value":5.5506940253470125,"rank":322},"Power-up Percent":{"value":0.13,"rank":262},"Time Played":{"value":134625,"rank":385},"Disconnects":{"value":25,"rank":341},"Disconnects Per Game":{"value":0.046992481203007516,"rank":140}}},"Rolling 300":{"All":{"Win Percent":{"value":0.7425347572033045,"rank":145},"Points":{"value":5932,"rank":292},"Points Per Game":{"value":19.773333333333333,"rank":293},"Games":{"value":300,"rank":395},"Games Per Hour":{"value":14.623446258834997,"rank":40},"Wins":{"value":222,"rank":123},"Ties":{"value":4,"rank":135},"Losses":{"value":68,"rank":316},"Saves":{"value":5,"rank":137},"Save Percent":{"value":0.83,"rank":7},"Tags":{"value":2365,"rank":74},"Tags Per Game":{"value":7.883333333333334,"rank":74},"Tags Per Hour":{"value":115.28150134048256,"rank":25},"Popped":{"value":1576,"rank":385},"Popped Per Game":{"value":5.253333333333333,"rank":391},"Popped Per Hour":{"value":76.82183767974652,"rank":327},"Tags Per Pop":{"value":1.5006345177664975,"rank":33},"Grabs":{"value":1482,"rank":312},"Grabs Per Game":{"value":0.9403553299492385,"rank":88},"Grabs Per Hour":{"value":72.2398245186449,"rank":203},"Captures":{"value":281,"rank":100},"Captures Per Game":{"value":0.9366666666666666,"rank":100},"Captures Per Hour":{"value":13.697294662442115,"rank":68},"Captures Per Grab":{"value":0.18960863697705804,"rank":43},"Hold":{"value":12098,"rank":309},"Hold Per Game":{"value":40.32666666666667,"rank":311},"Hold Per Grab":{"value":8.163292847503374,"rank":271},"Hold Per Hour":{"value":589.7148427979528,"rank":253},"Hold Per Cap":{"value":43.05338078291815,"rank":429},"Prevent":{"value":11600,"rank":116},"Prevent Per Game":{"value":38.666666666666664,"rank":117},"Prevent Per Hour":{"value":565.4399220082865,"rank":59},"Returns":{"value":2017,"rank":40},"Returns Per Game":{"value":6.723333333333334,"rank":40},"Returns Per Hour":{"value":98.31830368023398,"rank":14},"Support":{"value":4025,"rank":330},"Support Per Game":{"value":13.416666666666666,"rank":336},"Support Per Hour":{"value":196.1979039727029,"rank":284},"Non-Return Tags":{"value":348,"rank":316},"Prevent Per Return":{"value":5.751115518096182,"rank":273},"Power-up Percent":{"value":0.15,"rank":225},"Time Played":{"value":73854,"rank":386},"Disconnects":{"value":5,"rank":205},"Disconnects Per Game":{"value":0.016666666666666666,"rank":205}},"CTF":{"Win Percent":{"value":0.7570945945945946,"rank":101},"Points":{"value":4282,"rank":252},"Points Per Game":{"value":19.91627906976744,"rank":305},"Games":{"value":215,"rank":137},"Games Per Hour":{"value":14.597438847292684,"rank":36},"Wins":{"value":162,"rank":110},"Ties":{"value":4,"rank":76},"Losses":{"value":46,"rank":344},"Saves":{"value":5,"rank":80},"Save Percent":{"value":0.83,"rank":12},"Tags":{"value":1710,"rank":66},"Tags Per Game":{"value":7.953488372093023,"rank":70},"Tags Per Hour":{"value":116.10056013428137,"rank":24},"Popped":{"value":932,"rank":390},"Popped Per Game":{"value":4.334883720930232,"rank":407},"Popped Per Hour":{"value":63.27820002640363,"rank":369},"Tags Per Pop":{"value":1.8347639484978542,"rank":30},"Grabs":{"value":814,"rank":351},"Grabs Per Game":{"value":0.8733905579399142,"rank":158},"Grabs Per Hour":{"value":55.26658242649416,"rank":316},"Captures":{"value":174,"rank":135},"Captures Per Game":{"value":0.8093023255813954,"rank":138},"Captures Per Hour":{"value":11.813741206646172,"rank":95},"Captures Per Grab":{"value":0.21375921375921375,"rank":28},"Hold":{"value":7884,"rank":343},"Hold Per Game":{"value":36.669767441860465,"rank":362},"Hold Per Grab":{"value":9.685503685503685,"rank":295},"Hold Per Hour":{"value":535.2846877770024,"rank":325},"Hold Per Cap":{"value":45.310344827586206,"rank":429},"Prevent":{"value":6851,"rank":70},"Prevent Per Game":{"value":31.865116279069767,"rank":82},"Prevent Per Hour":{"value":465.1490862455915,"rank":47},"Returns":{"value":1455,"rank":37},"Returns Per Game":{"value":6.767441860465116,"rank":38},"Returns Per Hour":{"value":98.78731871074817,"rank":14},"Support":{"value":1938,"rank":320},"Support Per Game":{"value":9.013953488372094,"rank":322},"Support Per Hour":{"value":131.58063481885222,"rank":228},"Non-Return Tags":{"value":255,"rank":305},"Prevent Per Return":{"value":4.708591065292096,"rank":171},"Power-up Percent":{"value":0.14,"rank":252},"Time Played":{"value":53023,"rank":361},"Disconnects":{"value":2,"rank":288},"Disconnects Per Game":{"value":0.009302325581395349,"rank":272}},"Neutral":{"Win Percent":{"value":0,"rank":420},"Points":{"value":1650,"rank":256},"Points Per Game":{"value":19.41176470588235,"rank":213},"Games":{"value":85,"rank":300},"Games Per Hour":{"value":14.689645240266909,"rank":129},"Wins":{"value":60,"rank":168},"Ties":{"value":0,"rank":416},"Losses":{"value":22,"rank":259},"Saves":{"value":0,"rank":420},"Save Percent":{"value":0,"rank":420},"Tags":{"value":655,"rank":173},"Tags Per Game":{"value":7.705882352941177,"rank":110},"Tags Per Hour":{"value":113.19667802793913,"rank":46},"Popped":{"value":644,"rank":248},"Popped Per Game":{"value":7.576470588235294,"rank":187},"Popped Per Hour":{"value":111.29566511449282,"rank":73},"Tags Per Pop":{"value":1.0170807453416149,"rank":91},"Grabs":{"value":668,"rank":133},"Grabs Per Game":{"value":1.0372670807453417,"rank":32},"Grabs Per Hour":{"value":115.44332965292114,"rank":21},"Captures":{"value":107,"rank":52},"Captures Per Game":{"value":1.2588235294117647,"rank":35},"Captures Per Hour":{"value":18.491671067159523,"rank":39},"Captures Per Grab":{"value":0.1601796407185629,"rank":75},"Hold":{"value":4214,"rank":110},"Hold Per Game":{"value":49.576470588235296,"rank":87},"Hold Per Grab":{"value":6.308383233532934,"rank":148},"Hold Per Hour":{"value":728.260765205703,"rank":70},"Hold Per Cap":{"value":39.38317757009346,"rank":364},"Prevent":{"value":4749,"rank":268},"Prevent Per Game":{"value":55.870588235294115,"rank":236},"Prevent Per Hour":{"value":820.7191205415007,"rank":172},"Returns":{"value":562,"rank":129},"Returns Per Game":{"value":6.6117647058823525,"rank":61},"Returns Per Hour":{"value":97.12447794152945,"rank":20},"Support":{"value":2087,"rank":324},"Support Per Game":{"value":24.55294117647059,"rank":322},"Support Per Hour":{"value":360.6739954874946,"rank":301},"Non-Return Tags":{"value":93,"rank":302},"Prevent Per Return":{"value":8.45017793594306,"rank":319},"Power-up Percent":{"value":0.17,"rank":196},"Time Played":{"value":20831,"rank":311},"Disconnects":{"value":3,"rank":99},"Disconnects Per Game":{"value":0.03529411764705882,"rank":87}}}}
