{"name":"Cannon Ball","id":405,"All Time":{"Daily":{"Win Percent":{"value":0,"rank":154},"Points":{"value":0,"rank":245},"Points Per Game":{"value":0,"rank":245},"Games":{"value":0,"rank":245},"Games Per Hour":{"value":0,"rank":245},"Wins":{"value":0,"rank":237},"Ties":{"value":0,"rank":158},"Losses":{"value":0,"rank":237},"Saves":{"value":0,"rank":154},"Save Percent":{"value":0,"rank":154},"Tags":{"value":0,"rank":245},"Tags Per Game":{"value":0,"rank":245},"Tags Per Hour":{"value":0,"rank":245},"Popped":{"value":0,"rank":244},"Popped Per Game":{"value":0,"rank":244},"Popped Per Hour":{"value":0,"rank":244},"Tags Per Pop":{"value":0,"rank":245},"Grabs":{"value":0,"rank":244},"Grabs Per Game":{"value":0,"rank":244},"Grabs Per Hour":{"value":0,"rank":244},"Captures":{"value":0,"rank":236},"Captures Per Game":{"value":0,"rank":236},"Captures Per Hour":{"value":0,"rank":236},"Captures Per Grab":{"value":0,"rank":236},"Hold":{"value":0,"rank":244},"Hold Per Game":{"value":0,"rank":244},"Hold Per Grab":{"value":0,"rank":244},"Hold Per Hour":{"value":0,"rank":244},"Hold Per Cap":{"value":0,"rank":244},"Prevent":{"value":0,"rank":245},"Prevent Per Game":{"value":0,"rank":245},"Prevent Per Hour":{"value":0,"rank":245},"Returns":{"value":0,"rank":245},"Returns Per Game":{"value":0,"rank":245},"Returns Per Hour":{"value":0,"rank":245},"Support":{"value":0,"rank":244},"Support Per Game":{"value":0,"rank":244},"Support Per Hour":{"value":0,"rank":244},"Non-Return Tags":{"value":0,"rank":238},"Prevent Per Return":{"value":0,"rank":245},"Power-up Percent":{"value":0,"rank":239},"Time Played":{"value":0,"rank":245},"Disconnects":{"value":0,"rank":181},"Disconnects Per Game":{"value":0,"rank":181}},"Weekly":{"Win Percent":{"value":0,"rank":238},"Points":{"value":0,"rank":311},"Points Per Game":{"value":0,"rank":311},"Games":{"value":0,"rank":311},"Games Per Hour":{"value":0,"rank":311},"Wins":{"value":0,"rank":310},"Ties":{"value":0,"rank":250},"Losses":{"value":0,"rank":309},"Saves":{"value":0,"rank":238},"Save Percent":{"value":0,"rank":238},"Tags":{"value":0,"rank":311},"Tags Per Game":{"value":0,"rank":311},"Tags Per Hour":{"value":0,"rank":311},"Popped":{"value":0,"rank":311},"Popped Per Game":{"value":0,"rank":311},"Popped Per Hour":{"value":0,"rank":311},"Tags Per Pop":{"value":0,"rank":311},"Grabs":{"value":0,"rank":311},"Grabs Per Game":{"value":0,"rank":311},"Grabs Per Hour":{"value":0,"rank":311},"Captures":{"value":0,"rank":310},"Captures Per Game":{"value":0,"rank":310},"Captures Per Hour":{"value":0,"rank":310},"Captures Per Grab":{"value":0,"rank":310},"Hold":{"value":0,"rank":311},"Hold Per Game":{"value":0,"rank":311},"Hold Per Grab":{"value":0,"rank":311},"Hold Per Hour":{"value":0,"rank":311},"Hold Per Cap":{"value":0,"rank":311},"Prevent":{"value":0,"rank":310},"Prevent Per Game":{"value":0,"rank":310},"Prevent Per Hour":{"value":0,"rank":310},"Returns":{"value":0,"rank":311},"Returns Per Game":{"value":0,"rank":311},"Returns Per Hour":{"value":0,"rank":311},"Support":{"value":0,"rank":310},"Support Per Game":{"value":0,"rank":310},"Support Per Hour":{"value":0,"rank":310},"Non-Return Tags":{"value":0,"rank":309},"Prevent Per Return":{"value":0,"rank":310},"Power-up Percent":{"value":0,"rank":311},"Time Played":{"value":0,"rank":311},"Disconnects":{"value":0,"rank":272},"Disconnects Per Game":{"value":0,"rank":272}},"Monthly":{"Win Percent":{"value":0,"rank":305},"Points":{"value":0,"rank":328},"Points Per Game":{"value":0,"rank":328},"Games":{"value":0,"rank":329},"Games Per Hour":{"value":0,"rank":329},"Wins":{"value":0,"rank":327},"Ties":{"value":0,"rank":304},"Losses":{"value":0,"rank":324},"Saves":{"value":0,"rank":305},"Save Percent":{"value":0,"rank":305},"Tags":{"value":0,"rank":329},"Tags Per Game":{"value":0,"rank":329},"Tags Per Hour":{"value":0,"rank":329},"Popped":{"value":0,"rank":329},"Popped Per Game":{"value":0,"rank":329},"Popped Per Hour":{"value":0,"rank":329},"Tags Per Pop":{"value":0,"rank":329},"Grabs":{"value":0,"rank":329},"Grabs Per Game":{"value":0,"rank":329},"Grabs Per Hour":{"value":0,"rank":329},"Captures":{"value":0,"rank":326},"Captures Per Game":{"value":0,"rank":326},"Captures Per Hour":{"value":0,"rank":326},"Captures Per Grab":{"value":0,"rank":326},"Hold":{"value":0,"rank":329},"Hold Per Game":{"value":0,"rank":329},"Hold Per Grab":{"value":0,"rank":329},"Hold Per Hour":{"value":0,"rank":329},"Hold Per Cap":{"value":0,"rank":329},"Prevent":{"value":0,"rank":329},"Prevent Per Game":{"value":0,"rank":329},"Prevent Per Hour":{"value":0,"rank":329},"Returns":{"value":0,"rank":329},"Returns Per Game":{"value":0,"rank":329},"Returns Per Hour":{"value":0,"rank":329},"Support":{"value":0,"rank":329},"Support Per Game":{"value":0,"rank":329},"Support Per Hour":{"value":0,"rank":329},"Non-Return Tags":{"value":0,"rank":328},"Prevent Per Return":{"value":0,"rank":329},"Power-up Percent":{"value":0,"rank":329},"Time Played":{"value":0,"rank":329},"Disconnects":{"value":0,"rank":304},"Disconnects Per Game":{"value":0,"rank":304}},"All":{"Win Percent":{"value":0.7376237623762376,"rank":37},"Points":{"value":9280,"rank":388},"Points Per Game":{"value":22.634146341463413,"rank":20},"Games":{"value":410,"rank":395},"Games Per Hour":{"value":12.4663215060938,"rank":379},"Wins":{"value":298,"rank":392},"Ties":{"value":3,"rank":362},"Losses":{"value":99,"rank":399},"Saves":{"value":2,"rank":408},"Save Percent":{"value":0.25,"rank":335},"Tags":{"value":2370,"rank":404},"Tags Per Game":{"value":5.780487804878049,"rank":200},"Tags Per Hour":{"value":72.06141943766417,"rank":265},"Popped":{"value":2638,"rank":392},"Popped Per Game":{"value":6.434146341463415,"rank":149},"Popped Per Hour":{"value":80.21013690994012,"rank":249},"Tags Per Pop":{"value":0.8984078847611827,"rank":240},"Grabs":{"value":2459,"rank":389},"Grabs Per Game":{"value":0.9321455648218347,"rank":36},"Grabs Per Hour":{"value":74.76752337435282,"rank":93},"Captures":{"value":431,"rank":368},"Captures Per Game":{"value":1.051219512195122,"rank":28},"Captures Per Hour":{"value":13.104840412503485,"rank":45},"Captures Per Grab":{"value":0.1752745018300122,"rank":57},"Hold":{"value":27567,"rank":376},"Hold Per Game":{"value":67.23658536585366,"rank":15},"Hold Per Grab":{"value":11.21065473769825,"rank":39},"Hold Per Hour":{"value":838.1928901426533,"rank":41},"Hold Per Cap":{"value":63.96055684454756,"rank":329},"Prevent":{"value":11087,"rank":404},"Prevent Per Game":{"value":27.041463414634148,"rank":273},"Prevent Per Hour":{"value":337.10757692210234,"rank":305},"Returns":{"value":1881,"rank":402},"Returns Per Game":{"value":4.587804878048781,"rank":184},"Returns Per Hour":{"value":57.193050616981566,"rank":235},"Support":{"value":4977,"rank":404},"Support Per Game":{"value":12.139024390243902,"rank":272},"Support Per Hour":{"value":151.32898081909477,"rank":331},"Non-Return Tags":{"value":489,"rank":409},"Prevent Per Return":{"value":5.894205209994683,"rank":288},"Power-up Percent":{"value":0.16,"rank":162},"Time Played":{"value":118399,"rank":388},"Disconnects":{"value":4,"rank":399},"Disconnects Per Game":{"value":0.00975609756097561,"rank":361}}},"Rolling 300":{"All":{"Win Percent":{"value":0,"rank":398},"Points":{"value":6763,"rank":65},"Points Per Game":{"value":22.543333333333333,"rank":65},"Games":{"value":300,"rank":141},"Games Per Hour":{"value":12.45904665220802,"rank":342},"Wins":{"value":217,"rank":166},"Ties":{"value":3,"rank":165},"Losses":{"value":70,"rank":282},"Saves":{"value":0,"rank":416},"Save Percent":{"value":0,"rank":398},"Tags":{"value":1716,"rank":325},"Tags Per Game":{"value":5.72,"rank":327},"Tags Per Hour":{"value":71.26574685062987,"rank":347},"Popped":{"value":1977,"rank":141},"Popped Per Game":{"value":6.59,"rank":144},"Popped Per Hour":{"value":82.10511743805085,"rank":223},"Tags Per Pop":{"value":0.8679817905918058,"rank":326},"Grabs":{"value":1849,"rank":65},"Grabs Per Game":{"value":0.9352554375316136,"rank":95},"Grabs Per Hour":{"value":76.78925753310877,"rank":128},"Captures":{"value":319,"rank":45},"Captures Per Game":{"value":1.0633333333333332,"rank":45},"Captures Per Hour":{"value":13.24811960684786,"rank":80},"Captures Per Grab":{"value":0.17252568956192538,"rank":81},"Hold":{"value":20671,"rank":26},"Hold Per Game":{"value":68.90333333333334,"rank":26},"Hold Per Grab":{"value":11.179556517036236,"rank":46},"Hold Per Hour":{"value":858.4698444926399,"rank":44},"Hold Per Cap":{"value":64.79937304075236,"rank":262},"Prevent":{"value":8271,"rank":308},"Prevent Per Game":{"value":27.57,"rank":314},"Prevent Per Hour":{"value":343.4959162013751,"rank":345},"Returns":{"value":1342,"rank":316},"Returns Per Game":{"value":4.473333333333334,"rank":318},"Returns Per Hour":{"value":55.73346869087721,"rank":348},"Support":{"value":3749,"rank":365},"Support Per Game":{"value":12.496666666666666,"rank":370},"Support Per Hour":{"value":155.69655299709288,"rank":397},"Non-Return Tags":{"value":374,"rank":291},"Prevent Per Return":{"value":6.163189269746646,"rank":231},"Power-up Percent":{"value":0.16,"rank":186},"Time Played":{"value":86684,"rank":88},"Disconnects":{"value":4,"rank":211},"Disconnects Per Game":{"value":0.013333333333333334,"rank":211}},"CTF":{"Win Percent":{"value":0,"rank":398},"Points":{"value":5576,"rank":12},"Points Per Game":{"value":24.03448275862069,"rank":27},"Games":{"value":232,"rank":42},"Games Per Hour":{"value":11.77963950241178,"rank":391},"Wins":{"value":172,"rank":52},"Ties":{"value":3,"rank":98},"Losses":{"value":48,"rank":309},"Saves":{"value":0,"rank":398},"Save Percent":{"value":0,"rank":398},"Tags":{"value":1310,"rank":250},"Tags Per Game":{"value":5.646551724137931,"rank":313},"Tags Per Hour":{"value":66.51434374206652,"rank":346},"Popped":{"value":1520,"rank":33},"Popped Per Game":{"value":6.551724137931035,"rank":90},"Popped Per Hour":{"value":77.17694846407717,"rank":162},"Tags Per Pop":{"value":0.8618421052631579,"rank":333},"Grabs":{"value":1428,"rank":13},"Grabs Per Game":{"value":0.9394736842105263,"rank":61},"Grabs Per Hour":{"value":72.5057121096725,"rank":86},"Captures":{"value":247,"rank":28},"Captures Per Game":{"value":1.0646551724137931,"rank":38},"Captures Per Hour":{"value":12.541254125412541,"rank":77},"Captures Per Grab":{"value":0.17296918767507002,"rank":111},"Hold":{"value":18267,"rank":11},"Hold Per Game":{"value":78.73706896551724,"rank":18},"Hold Per Grab":{"value":12.792016806722689,"rank":76},"Hold Per Hour":{"value":927.4942878903274,"rank":37},"Hold Per Cap":{"value":73.95546558704453,"rank":264},"Prevent":{"value":4534,"rank":207},"Prevent Per Game":{"value":19.54310344827586,"rank":254},"Prevent Per Hour":{"value":230.2107133790302,"rank":275},"Returns":{"value":995,"rank":233},"Returns Per Game":{"value":4.288793103448276,"rank":300},"Returns Per Hour":{"value":50.52043665905052,"rank":347},"Support":{"value":2160,"rank":193},"Support Per Game":{"value":9.310344827586206,"rank":304},"Support Per Hour":{"value":109.67250571210967,"rank":385},"Non-Return Tags":{"value":315,"rank":209},"Prevent Per Return":{"value":4.55678391959799,"rank":186},"Power-up Percent":{"value":0.15,"rank":203},"Time Played":{"value":70902,"rank":11},"Disconnects":{"value":3,"rank":213},"Disconnects Per Game":{"value":0.01293103448275862,"rank":236}},"Neutral":{"Win Percent":{"value":0,"rank":305},"Points":{"value":1187,"rank":393},"Points Per Game":{"value":17.455882352941178,"rank":330},"Games":{"value":68,"rank":384},"Games Per Hour":{"value":15.511342035230008,"rank":61},"Wins":{"value":45,"rank":333},"Ties":{"value":0,"rank":270},"Losses":{"value":22,"rank":250},"Saves":{"value":0,"rank":305},"Save Percent":{"value":0,"rank":305},"Tags":{"value":406,"rank":389},"Tags Per Game":{"value":5.970588235294118,"rank":344},"Tags Per Hour":{"value":92.6118362691674,"rank":258},"Popped":{"value":457,"rank":386},"Popped Per Game":{"value":6.720588235294118,"rank":323},"Popped Per Hour":{"value":104.24534279558992,"rank":179},"Tags Per Pop":{"value":0.888402625820569,"rank":288},"Grabs":{"value":421,"rank":374},"Grabs Per Game":{"value":0.9212253829321663,"rank":209},"Grabs Per Hour":{"value":96.03345583576225,"rank":199},"Captures":{"value":72,"rank":214},"Captures Per Game":{"value":1.0588235294117647,"rank":115},"Captures Per Hour":{"value":16.423773919655304,"rank":72},"Captures Per Grab":{"value":0.171021377672209,"rank":49},"Hold":{"value":2404,"rank":359},"Hold Per Game":{"value":35.35294117647059,"rank":283},"Hold Per Grab":{"value":5.710213776722091,"rank":221},"Hold Per Hour":{"value":548.3715625396021,"rank":230},"Hold Per Cap":{"value":33.388888888888886,"rank":418},"Prevent":{"value":3737,"rank":358},"Prevent Per Game":{"value":54.955882352941174,"rank":245},"Prevent Per Hour":{"value":852.4394880243315,"rank":136},"Returns":{"value":347,"rank":367},"Returns Per Game":{"value":5.102941176470588,"rank":299},"Returns Per Hour":{"value":79.15346597389431,"rank":189},"Support":{"value":1589,"rank":383},"Support Per Game":{"value":23.36764705882353,"rank":347},"Support Per Hour":{"value":362.46356608794827,"rank":294},"Non-Return Tags":{"value":59,"rank":401},"Prevent Per Return":{"value":10.769452449567723,"rank":177},"Power-up Percent":{"value":0.21,"rank":110},"Time Played":{"value":15782,"rank":391},"Disconnects":{"value":1,"rank":174},"Disconnects Per Game":{"value":0.014705882352941176,"rank":152}}}}
