{"name":"CoolHandJuke","id":5,"All Time":{"Daily":{"Win Percent":{"value":0,"rank":229},"Points":{"value":642,"rank":10},"Points Per Game":{"value":21.4,"rank":51},"Games":{"value":30,"rank":16},"Games Per Hour":{"value":11.799410029498524,"rank":114},"Wins":{"value":14,"rank":21},"Ties":{"value":0,"rank":233},"Losses":{"value":14,"rank":15},"Saves":{"value":0,"rank":229},"Save Percent":{"value":0,"rank":229},"Tags":{"value":212,"rank":9},"Tags Per Game":{"value":7.066666666666666,"rank":35},"Tags Per Hour":{"value":83.38249754178958,"rank":51},"Popped":{"value":213,"rank":14},"Popped Per Game":{"value":7.1,"rank":57},"Popped Per Hour":{"value":83.77581120943952,"rank":97},"Tags Per Pop":{"value":0.9953051643192489,"rank":55},"Grabs":{"value":173,"rank":13},"Grabs Per Game":{"value":0.812206572769953,"rank":66},"Grabs Per Hour":{"value":68.04326450344149,"rank":90},"Captures":{"value":16,"rank":14},"Captures Per Game":{"value":0.5333333333333333,"rank":66},"Captures Per Hour":{"value":6.293018682399214,"rank":68},"Captures Per Grab":{"value":0.09248554913294797,"rank":72},"Hold":{"value":1084,"rank":19},"Hold Per Game":{"value":36.13333333333333,"rank":92},"Hold Per Grab":{"value":6.265895953757226,"rank":121},"Hold Per Hour":{"value":426.3520157325467,"rank":121},"Hold Per Cap":{"value":67.75,"rank":109},"Prevent":{"value":1065,"rank":16},"Prevent Per Game":{"value":35.5,"rank":56},"Prevent Per Hour":{"value":418.87905604719765,"rank":73},"Returns":{"value":171,"rank":11},"Returns Per Game":{"value":5.7,"rank":38},"Returns Per Hour":{"value":67.2566371681416,"rank":53},"Support":{"value":579,"rank":11},"Support Per Game":{"value":19.3,"rank":45},"Support Per Hour":{"value":227.72861356932154,"rank":65},"Non-Return Tags":{"value":41,"rank":11},"Prevent Per Return":{"value":6.228070175438597,"rank":93},"Power-up Percent":{"value":0.09,"rank":88},"Time Played":{"value":9153,"rank":12},"Disconnects":{"value":0,"rank":242},"Disconnects Per Game":{"value":0,"rank":242}},"Weekly":{"Win Percent":{"value":0,"rank":293},"Points":{"value":2763,"rank":43},"Points Per Game":{"value":20.619402985074625,"rank":93},"Games":{"value":134,"rank":60},"Games Per Hour":{"value":11.876507952139447,"rank":211},"Wins":{"value":61,"rank":80},"Ties":{"value":1,"rank":111},"Losses":{"value":66,"rank":40},"Saves":{"value":0,"rank":293},"Save Percent":{"value":0,"rank":293},"Tags":{"value":890,"rank":41},"Tags Per Game":{"value":6.641791044776119,"rank":87},"Tags Per Hour":{"value":78.88128415973213,"rank":136},"Popped":{"value":971,"rank":47},"Popped Per Game":{"value":7.246268656716418,"rank":52},"Popped Per Hour":{"value":86.06036732483135,"rank":114},"Tags Per Pop":{"value":0.9165808444902163,"rank":136},"Grabs":{"value":741,"rank":55},"Grabs Per Game":{"value":0.7631307929969104,"rank":182},"Grabs Per Hour":{"value":65.67531636220396,"rank":159},"Captures":{"value":51,"rank":110},"Captures Per Game":{"value":0.3805970149253731,"rank":192},"Captures Per Hour":{"value":4.52016347432173,"rank":203},"Captures Per Grab":{"value":0.06882591093117409,"rank":213},"Hold":{"value":4673,"rank":92},"Hold Per Game":{"value":34.87313432835821,"rank":185},"Hold Per Grab":{"value":6.3063427800269904,"rank":223},"Hold Per Hour":{"value":414.1710571667734,"rank":205},"Hold Per Cap":{"value":91.62745098039215,"rank":78},"Prevent":{"value":4560,"rank":72},"Prevent Per Game":{"value":34.02985074626866,"rank":139},"Prevent Per Hour":{"value":404.15579299817813,"rank":161},"Returns":{"value":732,"rank":37},"Returns Per Game":{"value":5.462686567164179,"rank":77},"Returns Per Hour":{"value":64.8776404549707,"rank":112},"Support":{"value":2814,"rank":27},"Support Per Game":{"value":21,"rank":24},"Support Per Hour":{"value":249.40666699492834,"rank":47},"Non-Return Tags":{"value":158,"rank":68},"Prevent Per Return":{"value":6.229508196721311,"rank":173},"Power-up Percent":{"value":0.08,"rank":189},"Time Played":{"value":40618,"rank":47},"Disconnects":{"value":2,"rank":128},"Disconnects Per Game":{"value":0.014925373134328358,"rank":142}},"Monthly":{"Win Percent":{"value":0,"rank":340},"Points":{"value":5110,"rank":178},"Points Per Game":{"value":18.514492753623188,"rank":188},"Games":{"value":276,"rank":177},"Games Per Hour":{"value":13.035948569929152,"rank":135},"Wins":{"value":122,"rank":190},"Ties":{"value":2,"rank":187},"Losses":{"value":133,"rank":148},"Saves":{"value":0,"rank":340},"Save Percent":{"value":0,"rank":340},"Tags":{"value":1666,"rank":172},"Tags Per Game":{"value":6.036231884057971,"rank":164},"Tags Per Hour":{"value":78.68800839674626,"rank":172},"Popped":{"value":1815,"rank":177},"Popped Per Game":{"value":6.576086956521739,"rank":130},"Popped Per Hour":{"value":85.72553135659932,"rank":130},"Tags Per Pop":{"value":0.9179063360881543,"rank":160},"Grabs":{"value":1369,"rank":178},"Grabs Per Game":{"value":0.7542699724517906,"rank":221},"Grabs Per Hour":{"value":64.66019417475728,"rank":188},"Captures":{"value":93,"rank":208},"Captures Per Game":{"value":0.33695652173913043,"rank":232},"Captures Per Hour":{"value":4.392547887693518,"rank":236},"Captures Per Grab":{"value":0.0679327976625274,"rank":241},"Hold":{"value":8615,"rank":190},"Hold Per Game":{"value":31.213768115942027,"rank":230},"Hold Per Grab":{"value":6.292914536157779,"rank":252},"Hold Per Hour":{"value":406.90107583311465,"rank":233},"Hold Per Cap":{"value":92.63440860215054,"rank":60},"Prevent":{"value":9361,"rank":176},"Prevent Per Game":{"value":33.916666666666664,"rank":151},"Prevent Per Hour":{"value":442.13592233009706,"rank":149},"Returns":{"value":1376,"rank":170},"Returns Per Game":{"value":4.9855072463768115,"rank":132},"Returns Per Hour":{"value":64.99081605877721,"rank":141},"Support":{"value":5071,"rank":173},"Support Per Game":{"value":18.3731884057971,"rank":66},"Support Per Hour":{"value":239.51193912358957,"rank":62},"Non-Return Tags":{"value":290,"rank":187},"Prevent Per Return":{"value":6.803052325581396,"rank":147},"Power-up Percent":{"value":0.08,"rank":213},"Time Played":{"value":76220,"rank":177},"Disconnects":{"value":10,"rank":136},"Disconnects Per Game":{"value":0.036231884057971016,"rank":121}},"All":{"Win Percent":{"value":0.43777313624678665,"rank":372},"Points":{"value":92663,"rank":228},"Points Per Game":{"value":16.19416288011185,"rank":374},"Games":{"value":5722,"rank":212},"Games Per Hour":{"value":13.70894643320622,"rank":143},"Wins":{"value":2477,"rank":243},"Ties":{"value":29,"rank":215},"Losses":{"value":2832,"rank":156},"Saves":{"value":18,"rank":253},"Save Percent":{"value":0.22,"rank":375},"Tags":{"value":28440,"rank":221},"Tags Per Game":{"value":4.970290108353723,"rank":330},"Tags Per Hour":{"value":68.13744085291592,"rank":311},"Popped":{"value":34340,"rank":208},"Popped Per Game":{"value":6.00139811254806,"rank":249},"Popped Per Hour":{"value":82.27284524926628,"rank":213},"Tags Per Pop":{"value":0.8281887012230634,"rank":284},"Grabs":{"value":22338,"rank":243},"Grabs Per Game":{"value":0.6504950495049505,"rank":404},"Grabs Per Hour":{"value":53.518078543334596,"rank":368},"Captures":{"value":1599,"rank":268},"Captures Per Game":{"value":0.27944774554351626,"rank":403},"Captures Per Hour":{"value":3.830934174536307,"rank":399},"Captures Per Grab":{"value":0.07158205748052646,"rank":379},"Hold":{"value":155187,"rank":264},"Hold Per Game":{"value":27.121111499475706,"rank":392},"Hold Per Grab":{"value":6.947219983883964,"rank":378},"Hold Per Hour":{"value":371.80186475532577,"rank":392},"Hold Per Cap":{"value":97.05253283302063,"rank":59},"Prevent":{"value":188259,"rank":179},"Prevent Per Game":{"value":32.90090877315624,"rank":163},"Prevent Per Hour":{"value":451.0367959750035,"rank":138},"Returns":{"value":23408,"rank":213},"Returns Per Game":{"value":4.090877315623907,"rank":271},"Returns Per Hour":{"value":56.08161798470661,"rank":254},"Support":{"value":71599,"rank":209},"Support Per Game":{"value":12.512932541069556,"rank":254},"Support Per Hour":{"value":171.53912192784554,"rank":249},"Non-Return Tags":{"value":5032,"rank":244},"Prevent Per Return":{"value":8.042506835269993,"rank":98},"Power-up Percent":{"value":0.08,"rank":369},"Time Played":{"value":1502610,"rank":216},"Disconnects":{"value":321,"rank":131},"Disconnects Per Game":{"value":0.05609926599091227,"rank":115}}},"Rolling 300":{"All":{"Win Percent":{"value":0,"rank":409},"Points":{"value":5631,"rank":336},"Points Per Game":{"value":18.77,"rank":338},"Games":{"value":300,"rank":217},"Games Per Hour":{"value":12.896292315959162,"rank":262},"Wins":{"value":133,"rank":373},"Ties":{"value":3,"rank":177},"Losses":{"value":145,"rank":32},"Saves":{"value":0,"rank":422},"Save Percent":{"value":0,"rank":409},"Tags":{"value":1849,"rank":274},"Tags Per Game":{"value":6.163333333333333,"rank":276},"Tags Per Hour":{"value":79.48414830736164,"rank":294},"Popped":{"value":1985,"rank":130},"Popped Per Game":{"value":6.616666666666666,"rank":133},"Popped Per Hour":{"value":85.33046749059646,"rank":159},"Tags Per Pop":{"value":0.9314861460957179,"rank":286},"Grabs":{"value":1496,"rank":306},"Grabs Per Game":{"value":0.7536523929471033,"rank":374},"Grabs Per Hour":{"value":64.30951101558303,"rank":330},"Captures":{"value":97,"rank":398},"Captures Per Game":{"value":0.3233333333333333,"rank":402},"Captures Per Hour":{"value":4.169801182160129,"rank":402},"Captures Per Grab":{"value":0.06483957219251336,"rank":412},"Hold":{"value":9458,"rank":382},"Hold Per Game":{"value":31.526666666666667,"rank":385},"Hold Per Grab":{"value":6.322192513368984,"rank":408},"Hold Per Hour":{"value":406.57710908113916,"rank":391},"Hold Per Cap":{"value":97.50515463917526,"rank":43},"Prevent":{"value":10499,"rank":180},"Prevent Per Game":{"value":34.99666666666667,"rank":184},"Prevent Per Hour":{"value":451.3272434175174,"rank":188},"Returns":{"value":1524,"rank":225},"Returns Per Game":{"value":5.08,"rank":225},"Returns Per Hour":{"value":65.51316496507255,"rank":243},"Support":{"value":5607,"rank":43},"Support Per Game":{"value":18.69,"rank":43},"Support Per Hour":{"value":241.03170338527673,"rank":52},"Non-Return Tags":{"value":325,"rank":349},"Prevent Per Return":{"value":6.889107611548557,"rank":152},"Power-up Percent":{"value":0.08,"rank":371},"Time Played":{"value":83745,"rank":167},"Disconnects":{"value":10,"rank":122},"Disconnects Per Game":{"value":0.03333333333333333,"rank":124}},"CTF":{"Win Percent":{"value":0,"rank":409},"Points":{"value":3748,"rank":364},"Points Per Game":{"value":19.419689119170986,"rank":330},"Games":{"value":193,"rank":389},"Games Per Hour":{"value":12.595855767661936,"rank":270},"Wins":{"value":88,"rank":370},"Ties":{"value":2,"rank":207},"Losses":{"value":88,"rank":71},"Saves":{"value":0,"rank":409},"Save Percent":{"value":0,"rank":409},"Tags":{"value":1199,"rank":306},"Tags Per Game":{"value":6.212435233160622,"rank":253},"Tags Per Hour":{"value":78.25093816283244,"rank":266},"Popped":{"value":1188,"rank":223},"Popped Per Game":{"value":6.155440414507772,"rank":135},"Popped Per Hour":{"value":77.53303964757708,"rank":157},"Tags Per Pop":{"value":1.0092592592592593,"rank":265},"Grabs":{"value":859,"rank":320},"Grabs Per Game":{"value":0.7230639730639731,"rank":364},"Grabs Per Hour":{"value":56.06134769130364,"rank":301},"Captures":{"value":65,"rank":383},"Captures Per Game":{"value":0.33678756476683935,"rank":376},"Captures Per Hour":{"value":4.242127590145212,"rank":379},"Captures Per Grab":{"value":0.07566938300349244,"rank":393},"Hold":{"value":6728,"rank":382},"Hold Per Game":{"value":34.86010362694301,"rank":374},"Hold Per Grab":{"value":7.832363213038417,"rank":394},"Hold Per Hour":{"value":439.0928373307228,"rank":381},"Hold Per Cap":{"value":103.50769230769231,"rank":77},"Prevent":{"value":4077,"rank":253},"Prevent Per Game":{"value":21.124352331606218,"rank":228},"Prevent Per Hour":{"value":266.07929515418505,"rank":235},"Returns":{"value":955,"rank":271},"Returns Per Game":{"value":4.948186528497409,"rank":215},"Returns Per Hour":{"value":62.326643824441184,"rank":220},"Support":{"value":2451,"rank":70},"Support Per Game":{"value":12.699481865284975,"rank":30},"Support Per Hour":{"value":159.9608418991679,"rank":26},"Non-Return Tags":{"value":244,"rank":329},"Prevent Per Return":{"value":4.269109947643979,"rank":222},"Power-up Percent":{"value":0.09,"rank":361},"Time Played":{"value":55161,"rank":318},"Disconnects":{"value":9,"rank":108},"Disconnects Per Game":{"value":0.046632124352331605,"rank":105}},"Neutral":{"Win Percent":{"value":0,"rank":338},"Points":{"value":1883,"rank":136},"Points Per Game":{"value":17.598130841121495,"rank":319},"Games":{"value":107,"rank":33},"Games Per Hour":{"value":13.476070528967254,"rank":273},"Wins":{"value":45,"rank":337},"Ties":{"value":1,"rank":134},"Losses":{"value":57,"rank":11},"Saves":{"value":0,"rank":338},"Save Percent":{"value":0,"rank":338},"Tags":{"value":650,"rank":184},"Tags Per Game":{"value":6.074766355140187,"rank":336},"Tags Per Hour":{"value":81.8639798488665,"rank":367},"Popped":{"value":797,"rank":76},"Popped Per Game":{"value":7.4485981308411215,"rank":202},"Popped Per Hour":{"value":100.37783375314861,"rank":263},"Tags Per Pop":{"value":0.8155583437892095,"rank":366},"Grabs":{"value":637,"rank":174},"Grabs Per Game":{"value":0.7992471769134254,"rank":372},"Grabs Per Hour":{"value":80.22670025188917,"rank":356},"Captures":{"value":32,"rank":389},"Captures Per Game":{"value":0.29906542056074764,"rank":408},"Captures Per Hour":{"value":4.030226700251889,"rank":413},"Captures Per Grab":{"value":0.05023547880690738,"rank":419},"Hold":{"value":2730,"rank":318},"Hold Per Game":{"value":25.514018691588785,"rank":379},"Hold Per Grab":{"value":4.285714285714286,"rank":401},"Hold Per Hour":{"value":343.8287153652393,"rank":386},"Hold Per Cap":{"value":85.3125,"rank":18},"Prevent":{"value":6422,"rank":81},"Prevent Per Game":{"value":60.018691588785046,"rank":166},"Prevent Per Hour":{"value":808.8161209068011,"rank":192},"Returns":{"value":569,"rank":118},"Returns Per Game":{"value":5.317757009345795,"rank":257},"Returns Per Hour":{"value":71.6624685138539,"rank":309},"Support":{"value":3156,"rank":62},"Support Per Game":{"value":29.49532710280374,"rank":164},"Support Per Hour":{"value":397.48110831234254,"rank":194},"Non-Return Tags":{"value":81,"rank":342},"Prevent Per Return":{"value":11.28646748681898,"rank":151},"Power-up Percent":{"value":0.06,"rank":378},"Time Played":{"value":28584,"rank":47},"Disconnects":{"value":1,"rank":192},"Disconnects Per Game":{"value":0.009345794392523364,"rank":243}}}}
